{
  "_mod": "Wed, 05 Jul 2017 23:29:46 GMT", 
  "_url": "https://conda.anaconda.org/quantopian/linux-64", 
  "info": {
    "arch": "x86_64", 
    "default_numpy_version": "1.7", 
    "default_python_version": "2.7", 
    "platform": "linux", 
    "subdir": "linux-64"
  }, 
  "packages": {
    "alembic-0.7.7-py27_0.tar.bz2": {
      "arch": "x86_64", 
      "binstar": {
        "channel": "main", 
        "owner_id": "52fa7ff95e76835e23a64c25", 
        "package_id": "57be098909b8ee63e6bba434"
      }, 
      "build": "py27_0", 
      "build_number": 0, 
      "depends": [
        "mako", 
        "python 2.7*", 
        "sqlalchemy >=0.7.6"
      ], 
      "has_prefix": true, 
      "license": "MIT", 
      "machine": "x86_64", 
      "md5": "2d490003cb86135c012fe0be8a9ab99f", 
      "name": "alembic", 
      "operatingsystem": "linux", 
      "platform": "linux", 
      "requires": [], 
      "size": 170354, 
      "subdir": "linux-64", 
      "target-triplet": "x86_64-any-linux", 
      "version": "0.7.7"
    }, 
    "alembic-0.7.7-py34_0.tar.bz2": {
      "arch": "x86_64", 
      "binstar": {
        "channel": "main", 
        "owner_id": "52fa7ff95e76835e23a64c25", 
        "package_id": "57be098909b8ee63e6bba434"
      }, 
      "build": "py34_0", 
      "build_number": 0, 
      "depends": [
        "mako", 
        "python 3.4*", 
        "sqlalchemy >=0.7.6"
      ], 
      "has_prefix": true, 
      "license": "MIT", 
      "machine": "x86_64", 
      "md5": "ccb98786c96c2368429946c9644258d3", 
      "name": "alembic", 
      "operatingsystem": "linux", 
      "platform": "linux", 
      "requires": [], 
      "size": 167296, 
      "subdir": "linux-64", 
      "target-triplet": "x86_64-any-linux", 
      "version": "0.7.7"
    }, 
    "bcolz-0.12.1-np111py27_0.tar.bz2": {
      "arch": "x86_64", 
      "binstar": {
        "channel": "main", 
        "owner_id": "52fa7ff95e76835e23a64c25", 
        "package_id": "56cd4006266fe4721e7bb00c"
      }, 
      "build": "np111py27_0", 
      "build_number": 0, 
      "depends": [
        "numpy 1.11*", 
        "python 2.7*"
      ], 
      "has_prefix": true, 
      "license": "BSD License", 
      "machine": "x86_64", 
      "md5": "6e7de5e3aea688485af8a535be655557", 
      "name": "bcolz", 
      "operatingsystem": "linux", 
      "platform": "linux", 
      "requires": [], 
      "size": 1014553, 
      "subdir": "linux-64", 
      "target-triplet": "x86_64-any-linux", 
      "version": "0.12.1"
    }, 
    "bcolz-0.12.1-np111py34_0.tar.bz2": {
      "arch": "x86_64", 
      "binstar": {
        "channel": "main", 
        "owner_id": "52fa7ff95e76835e23a64c25", 
        "package_id": "56cd4006266fe4721e7bb00c"
      }, 
      "build": "np111py34_0", 
      "build_number": 0, 
      "depends": [
        "numpy 1.11*", 
        "python 3.4*"
      ], 
      "has_prefix": true, 
      "license": "BSD License", 
      "machine": "x86_64", 
      "md5": "15806ab9775718a312c2fc5012a12864", 
      "name": "bcolz", 
      "operatingsystem": "linux", 
      "platform": "linux", 
      "requires": [], 
      "size": 1129492, 
      "subdir": "linux-64", 
      "target-triplet": "x86_64-any-linux", 
      "version": "0.12.1"
    }, 
    "bcolz-0.12.1-np19py27_0.tar.bz2": {
      "arch": "x86_64", 
      "binstar": {
        "channel": "main", 
        "owner_id": "52fa7ff95e76835e23a64c25", 
        "package_id": "56cd4006266fe4721e7bb00c"
      }, 
      "build": "np19py27_0", 
      "build_number": 0, 
      "depends": [
        "numpy 1.9*", 
        "python 2.7*"
      ], 
      "license": "BSD License", 
      "machine": "x86_64", 
      "md5": "ba203d90f41829096332535ada24416d", 
      "name": "bcolz", 
      "operatingsystem": "linux", 
      "platform": "linux", 
      "requires": [], 
      "size": 1021247, 
      "subdir": "linux-64", 
      "target-triplet": "x86_64-any-linux", 
      "version": "0.12.1"
    }, 
    "bcolz-0.12.1-np19py34_0.tar.bz2": {
      "arch": "x86_64", 
      "binstar": {
        "channel": "main", 
        "owner_id": "52fa7ff95e76835e23a64c25", 
        "package_id": "56cd4006266fe4721e7bb00c"
      }, 
      "build": "np19py34_0", 
      "build_number": 0, 
      "depends": [
        "numpy 1.9*", 
        "python 3.4*"
      ], 
      "license": "BSD License", 
      "machine": "x86_64", 
      "md5": "43821d21defcc90126d72585660de06b", 
      "name": "bcolz", 
      "operatingsystem": "linux", 
      "platform": "linux", 
      "requires": [], 
      "size": 1147665, 
      "subdir": "linux-64", 
      "target-triplet": "x86_64-any-linux", 
      "version": "0.12.1"
    }, 
    "cachetools-1.1.6-py27_0.tar.bz2": {
      "arch": "x86_64", 
      "binstar": {
        "channel": "main", 
        "owner_id": "52fa7ff95e76835e23a64c25", 
        "package_id": "5710ee4d878cc65fd99501cb"
      }, 
      "build": "py27_0", 
      "build_number": 0, 
      "depends": [
        "python 2.7*"
      ], 
      "license": "MIT License", 
      "machine": "x86_64", 
      "md5": "6139b745631d2a8175b979a525dd951f", 
      "name": "cachetools", 
      "operatingsystem": "linux", 
      "platform": "linux", 
      "requires": [], 
      "size": 24133, 
      "subdir": "linux-64", 
      "target-triplet": "x86_64-any-linux", 
      "version": "1.1.6"
    }, 
    "cachetools-1.1.6-py34_0.tar.bz2": {
      "arch": "x86_64", 
      "binstar": {
        "channel": "main", 
        "owner_id": "52fa7ff95e76835e23a64c25", 
        "package_id": "5710ee4d878cc65fd99501cb"
      }, 
      "build": "py34_0", 
      "build_number": 0, 
      "depends": [
        "python 3.4*"
      ], 
      "license": "MIT License", 
      "machine": "x86_64", 
      "md5": "3695bcb8beacd3f3e327d48785385d06", 
      "name": "cachetools", 
      "operatingsystem": "linux", 
      "platform": "linux", 
      "requires": [], 
      "size": 24631, 
      "subdir": "linux-64", 
      "target-triplet": "x86_64-any-linux", 
      "version": "1.1.6"
    }, 
    "conda-build-1.10alpha.0-py27_56_g0ff6f44.tar.bz2": {
      "arch": "x86_64", 
      "binstar": {
        "channel": "main", 
        "owner_id": "52fa7ff95e76835e23a64c25", 
        "package_id": "569981500eafa957d721a8b2"
      }, 
      "build": "py27_56_g0ff6f44", 
      "build_number": 56, 
      "depends": [
        "conda", 
        "jinja2", 
        "patchelf", 
        "python 2.7*"
      ], 
      "license": "BSD", 
      "machine": "x86_64", 
      "md5": "5c27a081d230d6a1561256f2c34cbc8f", 
      "name": "conda-build", 
      "operatingsystem": "linux", 
      "platform": "linux", 
      "requires": [], 
      "size": 213657, 
      "subdir": "linux-64", 
      "target-triplet": "x86_64-any-linux", 
      "version": "1.10alpha.0"
    }, 
    "conda-build-1.10alpha.0-py34_56_g0ff6f44.tar.bz2": {
      "arch": "x86_64", 
      "binstar": {
        "channel": "main", 
        "owner_id": "52fa7ff95e76835e23a64c25", 
        "package_id": "569981500eafa957d721a8b2"
      }, 
      "build": "py34_56_g0ff6f44", 
      "build_number": 56, 
      "depends": [
        "conda", 
        "jinja2", 
        "patchelf", 
        "python 3.4*"
      ], 
      "license": "BSD", 
      "machine": "x86_64", 
      "md5": "61721bf4c004f649ab44cf62b3f89b49", 
      "name": "conda-build", 
      "operatingsystem": "linux", 
      "platform": "linux", 
      "requires": [], 
      "size": 216321, 
      "subdir": "linux-64", 
      "target-triplet": "x86_64-any-linux", 
      "version": "1.10alpha.0"
    }, 
    "conda-build-1.10alpha.0-py35_56_g0ff6f44.tar.bz2": {
      "arch": "x86_64", 
      "binstar": {
        "channel": "main", 
        "owner_id": "52fa7ff95e76835e23a64c25", 
        "package_id": "569981500eafa957d721a8b2"
      }, 
      "build": "py35_56_g0ff6f44", 
      "build_number": 56, 
      "depends": [
        "conda", 
        "jinja2", 
        "patchelf", 
        "python 3.5*"
      ], 
      "license": "BSD", 
      "machine": "x86_64", 
      "md5": "736fe6d596dbaf5848c94b6ec68fefea", 
      "name": "conda-build", 
      "operatingsystem": "linux", 
      "platform": "linux", 
      "requires": [], 
      "size": 215446, 
      "subdir": "linux-64", 
      "target-triplet": "x86_64-any-linux", 
      "version": "1.10alpha.0"
    }, 
    "cyordereddict-0.2.2-py27_0.tar.bz2": {
      "arch": "x86_64", 
      "binstar": {
        "channel": "main", 
        "owner_id": "52fa7ff95e76835e23a64c25", 
        "package_id": "56998e6e0eafa9559021b338"
      }, 
      "binstar_build": "1.0", 
      "build": "py27_0", 
      "build_number": 0, 
      "depends": [
        "python 2.7*"
      ], 
      "license": "BSD License", 
      "machine": "x86_64", 
      "md5": "74547db9d3be8413cb596f5db3b471d3", 
      "name": "cyordereddict", 
      "operatingsystem": "linux", 
      "platform": "linux", 
      "requires": [], 
      "size": 125439, 
      "subdir": "linux-64", 
      "target-triplet": "x86_64-any-linux", 
      "version": "0.2.2"
    }, 
    "cyordereddict-0.2.2-py34_0.tar.bz2": {
      "arch": "x86_64", 
      "binstar": {
        "channel": "main", 
        "owner_id": "52fa7ff95e76835e23a64c25", 
        "package_id": "56998e6e0eafa9559021b338"
      }, 
      "binstar_build": "1.1", 
      "build": "py34_0", 
      "build_number": 0, 
      "depends": [
        "python 3.4*"
      ], 
      "license": "BSD License", 
      "machine": "x86_64", 
      "md5": "d05e4a53cb9be9d4af17f4a7c1be8f58", 
      "name": "cyordereddict", 
      "operatingsystem": "linux", 
      "platform": "linux", 
      "requires": [], 
      "size": 167986, 
      "subdir": "linux-64", 
      "target-triplet": "x86_64-any-linux", 
      "version": "0.2.2"
    }, 
    "empyrical-0.1.10-np110py27_0.tar.bz2": {
      "arch": "x86_64", 
      "binstar": {
        "channel": "main", 
        "owner_id": "52fa7ff95e76835e23a64c25", 
        "package_id": "57bcd13709b8ee3f8abb934b"
      }, 
      "build": "np110py27_0", 
      "build_number": 0, 
      "depends": [
        "bottleneck >=1.0.0", 
        "numpy 1.10*", 
        "pandas >=0.16.1", 
        "python 2.7*", 
        "scipy >=0.15.1"
      ], 
      "has_prefix": false, 
      "license": "Apache Software License", 
      "machine": "x86_64", 
      "md5": "7dcad92abfabd367d6736b7227e4dd5b", 
      "name": "empyrical", 
      "operatingsystem": "linux", 
      "platform": "linux", 
      "requires": [], 
      "size": 31011, 
      "subdir": "linux-64", 
      "target-triplet": "x86_64-any-linux", 
      "version": "0.1.10"
    }, 
    "empyrical-0.1.10-np110py34_0.tar.bz2": {
      "arch": "x86_64", 
      "binstar": {
        "channel": "main", 
        "owner_id": "52fa7ff95e76835e23a64c25", 
        "package_id": "57bcd13709b8ee3f8abb934b"
      }, 
      "build": "np110py34_0", 
      "build_number": 0, 
      "depends": [
        "bottleneck >=1.0.0", 
        "numpy 1.10*", 
        "pandas >=0.16.1", 
        "python 3.4*", 
        "scipy >=0.15.1"
      ], 
      "has_prefix": false, 
      "license": "Apache Software License", 
      "machine": "x86_64", 
      "md5": "3f2c8473363471cf1904297ed3a404dd", 
      "name": "empyrical", 
      "operatingsystem": "linux", 
      "platform": "linux", 
      "requires": [], 
      "size": 31640, 
      "subdir": "linux-64", 
      "target-triplet": "x86_64-any-linux", 
      "version": "0.1.10"
    }, 
    "empyrical-0.1.10-np19py27_0.tar.bz2": {
      "arch": "x86_64", 
      "binstar": {
        "channel": "main", 
        "owner_id": "52fa7ff95e76835e23a64c25", 
        "package_id": "57bcd13709b8ee3f8abb934b"
      }, 
      "build": "np19py27_0", 
      "build_number": 0, 
      "depends": [
        "bottleneck >=1.0.0", 
        "numpy 1.9*", 
        "pandas >=0.16.1", 
        "python 2.7*", 
        "scipy >=0.15.1"
      ], 
      "has_prefix": false, 
      "license": "Apache Software License", 
      "machine": "x86_64", 
      "md5": "1fdb60d980c7c7493bce8099755ecf67", 
      "name": "empyrical", 
      "operatingsystem": "linux", 
      "platform": "linux", 
      "requires": [], 
      "size": 31004, 
      "subdir": "linux-64", 
      "target-triplet": "x86_64-any-linux", 
      "version": "0.1.10"
    }, 
    "empyrical-0.1.10-np19py34_0.tar.bz2": {
      "arch": "x86_64", 
      "binstar": {
        "channel": "main", 
        "owner_id": "52fa7ff95e76835e23a64c25", 
        "package_id": "57bcd13709b8ee3f8abb934b"
      }, 
      "build": "np19py34_0", 
      "build_number": 0, 
      "depends": [
        "bottleneck >=1.0.0", 
        "numpy 1.9*", 
        "pandas >=0.16.1", 
        "python 3.4*", 
        "scipy >=0.15.1"
      ], 
      "has_prefix": false, 
      "license": "Apache Software License", 
      "machine": "x86_64", 
      "md5": "05aa244507d937e6e3585c89311f3ca6", 
      "name": "empyrical", 
      "operatingsystem": "linux", 
      "platform": "linux", 
      "requires": [], 
      "size": 31633, 
      "subdir": "linux-64", 
      "target-triplet": "x86_64-any-linux", 
      "version": "0.1.10"
    }, 
    "empyrical-0.1.11-np110py27_0.tar.bz2": {
      "arch": "x86_64", 
      "binstar": {
        "channel": "main", 
        "owner_id": "52fa7ff95e76835e23a64c25", 
        "package_id": "57bcd13709b8ee3f8abb934b"
      }, 
      "build": "np110py27_0", 
      "build_number": 0, 
      "depends": [
        "bottleneck >=1.0.0", 
        "numpy 1.10*", 
        "pandas >=0.16.1", 
        "python 2.7*", 
        "scipy >=0.15.1"
      ], 
      "has_prefix": false, 
      "license": "Apache Software License", 
      "machine": "x86_64", 
      "md5": "66b0b3231c4c89b3c36fdaee633d2cb5", 
      "name": "empyrical", 
      "operatingsystem": "linux", 
      "platform": "linux", 
      "requires": [], 
      "size": 31529, 
      "subdir": "linux-64", 
      "target-triplet": "x86_64-any-linux", 
      "version": "0.1.11"
    }, 
    "empyrical-0.1.11-np110py34_0.tar.bz2": {
      "arch": "x86_64", 
      "binstar": {
        "channel": "main", 
        "owner_id": "52fa7ff95e76835e23a64c25", 
        "package_id": "57bcd13709b8ee3f8abb934b"
      }, 
      "build": "np110py34_0", 
      "build_number": 0, 
      "depends": [
        "bottleneck >=1.0.0", 
        "numpy 1.10*", 
        "pandas >=0.16.1", 
        "python 3.4*", 
        "scipy >=0.15.1"
      ], 
      "has_prefix": false, 
      "license": "Apache Software License", 
      "machine": "x86_64", 
      "md5": "3c8a524906814b3c294be4e115ae46bb", 
      "name": "empyrical", 
      "operatingsystem": "linux", 
      "platform": "linux", 
      "requires": [], 
      "size": 32178, 
      "subdir": "linux-64", 
      "target-triplet": "x86_64-any-linux", 
      "version": "0.1.11"
    }, 
    "empyrical-0.1.11-np19py27_0.tar.bz2": {
      "arch": "x86_64", 
      "binstar": {
        "channel": "main", 
        "owner_id": "52fa7ff95e76835e23a64c25", 
        "package_id": "57bcd13709b8ee3f8abb934b"
      }, 
      "build": "np19py27_0", 
      "build_number": 0, 
      "depends": [
        "bottleneck >=1.0.0", 
        "numpy 1.9*", 
        "pandas >=0.16.1", 
        "python 2.7*", 
        "scipy >=0.15.1"
      ], 
      "has_prefix": false, 
      "license": "Apache Software License", 
      "machine": "x86_64", 
      "md5": "d7fc549ef0a054c163acf230441db2a0", 
      "name": "empyrical", 
      "operatingsystem": "linux", 
      "platform": "linux", 
      "requires": [], 
      "size": 31550, 
      "subdir": "linux-64", 
      "target-triplet": "x86_64-any-linux", 
      "version": "0.1.11"
    }, 
    "empyrical-0.1.11-np19py34_0.tar.bz2": {
      "arch": "x86_64", 
      "binstar": {
        "channel": "main", 
        "owner_id": "52fa7ff95e76835e23a64c25", 
        "package_id": "57bcd13709b8ee3f8abb934b"
      }, 
      "build": "np19py34_0", 
      "build_number": 0, 
      "depends": [
        "bottleneck >=1.0.0", 
        "numpy 1.9*", 
        "pandas >=0.16.1", 
        "python 3.4*", 
        "scipy >=0.15.1"
      ], 
      "has_prefix": false, 
      "license": "Apache Software License", 
      "machine": "x86_64", 
      "md5": "dd80aec2975793450149191d826cf69e", 
      "name": "empyrical", 
      "operatingsystem": "linux", 
      "platform": "linux", 
      "requires": [], 
      "size": 32171, 
      "subdir": "linux-64", 
      "target-triplet": "x86_64-any-linux", 
      "version": "0.1.11"
    }, 
    "empyrical-0.1.11-py27_0.tar.bz2": {
      "arch": "x86_64", 
      "binstar": {
        "channel": "main", 
        "owner_id": "52fa7ff95e76835e23a64c25", 
        "package_id": "57bcd13709b8ee3f8abb934b"
      }, 
      "build": "py27_0", 
      "build_number": 0, 
      "depends": [
        "bottleneck >=1.0.0", 
        "numpy >=1.9.2", 
        "pandas >=0.16.1", 
        "python 2.7*", 
        "scipy >=0.15.1"
      ], 
      "has_prefix": false, 
      "license": "Apache Software License", 
      "machine": "x86_64", 
      "md5": "d7fb12bf0182b2acc94bf57cf3745c14", 
      "name": "empyrical", 
      "operatingsystem": "linux", 
      "platform": "linux", 
      "requires": [], 
      "size": 31517, 
      "subdir": "linux-64", 
      "target-triplet": "x86_64-any-linux", 
      "version": "0.1.11"
    }, 
    "empyrical-0.1.11-py34_0.tar.bz2": {
      "arch": "x86_64", 
      "binstar": {
        "channel": "main", 
        "owner_id": "52fa7ff95e76835e23a64c25", 
        "package_id": "57bcd13709b8ee3f8abb934b"
      }, 
      "build": "py34_0", 
      "build_number": 0, 
      "depends": [
        "bottleneck >=1.0.0", 
        "numpy >=1.9.2", 
        "pandas >=0.16.1", 
        "python 3.4*", 
        "scipy >=0.15.1"
      ], 
      "has_prefix": false, 
      "license": "Apache Software License", 
      "machine": "x86_64", 
      "md5": "36aa37c169d223f50399ad5cb3e3c426", 
      "name": "empyrical", 
      "operatingsystem": "linux", 
      "platform": "linux", 
      "requires": [], 
      "size": 32168, 
      "subdir": "linux-64", 
      "target-triplet": "x86_64-any-linux", 
      "version": "0.1.11"
    }, 
    "empyrical-0.1.9-np110py27_0.tar.bz2": {
      "arch": "x86_64", 
      "binstar": {
        "channel": "main", 
        "owner_id": "52fa7ff95e76835e23a64c25", 
        "package_id": "57bcd13709b8ee3f8abb934b"
      }, 
      "build": "np110py27_0", 
      "build_number": 0, 
      "depends": [
        "bottleneck >=1.0.0", 
        "numpy 1.10*", 
        "pandas >=0.16.1", 
        "python 2.7*", 
        "scipy >=0.15.1"
      ], 
      "has_prefix": false, 
      "license": "Apache Software License", 
      "machine": "x86_64", 
      "md5": "e3ccf78097cfb48ccaca025cbb544a99", 
      "name": "empyrical", 
      "operatingsystem": "linux", 
      "platform": "linux", 
      "requires": [], 
      "size": 28629, 
      "subdir": "linux-64", 
      "target-triplet": "x86_64-any-linux", 
      "version": "0.1.9"
    }, 
    "empyrical-0.1.9-np110py34_0.tar.bz2": {
      "arch": "x86_64", 
      "binstar": {
        "channel": "main", 
        "owner_id": "52fa7ff95e76835e23a64c25", 
        "package_id": "57bcd13709b8ee3f8abb934b"
      }, 
      "build": "np110py34_0", 
      "build_number": 0, 
      "depends": [
        "bottleneck >=1.0.0", 
        "numpy 1.10*", 
        "pandas >=0.16.1", 
        "python 3.4*", 
        "scipy >=0.15.1"
      ], 
      "has_prefix": false, 
      "license": "Apache Software License", 
      "machine": "x86_64", 
      "md5": "efc0d0a632ff912add8127f282211324", 
      "name": "empyrical", 
      "operatingsystem": "linux", 
      "platform": "linux", 
      "requires": [], 
      "size": 29206, 
      "subdir": "linux-64", 
      "target-triplet": "x86_64-any-linux", 
      "version": "0.1.9"
    }, 
    "empyrical-0.1.9-np19py27_0.tar.bz2": {
      "arch": "x86_64", 
      "binstar": {
        "channel": "main", 
        "owner_id": "52fa7ff95e76835e23a64c25", 
        "package_id": "57bcd13709b8ee3f8abb934b"
      }, 
      "build": "np19py27_0", 
      "build_number": 0, 
      "depends": [
        "bottleneck >=1.0.0", 
        "numpy 1.9*", 
        "pandas >=0.16.1", 
        "python 2.7*", 
        "scipy >=0.15.1"
      ], 
      "has_prefix": false, 
      "license": "Apache Software License", 
      "machine": "x86_64", 
      "md5": "416222971456101b3cbe1a9147e355d2", 
      "name": "empyrical", 
      "operatingsystem": "linux", 
      "platform": "linux", 
      "requires": [], 
      "size": 28618, 
      "subdir": "linux-64", 
      "target-triplet": "x86_64-any-linux", 
      "version": "0.1.9"
    }, 
    "empyrical-0.1.9-np19py34_0.tar.bz2": {
      "arch": "x86_64", 
      "binstar": {
        "channel": "main", 
        "owner_id": "52fa7ff95e76835e23a64c25", 
        "package_id": "57bcd13709b8ee3f8abb934b"
      }, 
      "build": "np19py34_0", 
      "build_number": 0, 
      "depends": [
        "bottleneck >=1.0.0", 
        "numpy 1.9*", 
        "pandas >=0.16.1", 
        "python 3.4*", 
        "scipy >=0.15.1"
      ], 
      "has_prefix": false, 
      "license": "Apache Software License", 
      "machine": "x86_64", 
      "md5": "9bbb5a431ff0f31d0d8819bac4534816", 
      "name": "empyrical", 
      "operatingsystem": "linux", 
      "platform": "linux", 
      "requires": [], 
      "size": 29204, 
      "subdir": "linux-64", 
      "target-triplet": "x86_64-any-linux", 
      "version": "0.1.9"
    }, 
    "empyrical-0.2.0-py27_0.tar.bz2": {
      "arch": "x86_64", 
      "binstar": {
        "channel": "main", 
        "owner_id": "52fa7ff95e76835e23a64c25", 
        "package_id": "57bcd13709b8ee3f8abb934b"
      }, 
      "build": "py27_0", 
      "build_number": 0, 
      "depends": [
        "bottleneck >=1.0.0", 
        "numpy >=1.9.2", 
        "pandas >=0.16.1", 
        "python 2.7*", 
        "scipy >=0.15.1"
      ], 
      "has_prefix": false, 
      "license": "Apache Software License", 
      "machine": "x86_64", 
      "md5": "6fa342e3d77cb49efd7dee9361f5f01a", 
      "name": "empyrical", 
      "operatingsystem": "linux", 
      "platform": "linux", 
      "requires": [], 
      "size": 40376, 
      "subdir": "linux-64", 
      "target-triplet": "x86_64-any-linux", 
      "version": "0.2.0"
    }, 
    "empyrical-0.2.0-py34_0.tar.bz2": {
      "arch": "x86_64", 
      "binstar": {
        "channel": "main", 
        "owner_id": "52fa7ff95e76835e23a64c25", 
        "package_id": "57bcd13709b8ee3f8abb934b"
      }, 
      "build": "py34_0", 
      "build_number": 0, 
      "depends": [
        "bottleneck >=1.0.0", 
        "numpy >=1.9.2", 
        "pandas >=0.16.1", 
        "python 3.4*", 
        "scipy >=0.15.1"
      ], 
      "has_prefix": false, 
      "license": "Apache Software License", 
      "machine": "x86_64", 
      "md5": "706267565ea1bca3661b6134a5ce881a", 
      "name": "empyrical", 
      "operatingsystem": "linux", 
      "platform": "linux", 
      "requires": [], 
      "size": 41193, 
      "subdir": "linux-64", 
      "target-triplet": "x86_64-any-linux", 
      "version": "0.2.0"
    }, 
    "empyrical-0.2.1-py27_0.tar.bz2": {
      "arch": "x86_64", 
      "binstar": {
        "channel": "main", 
        "owner_id": "52fa7ff95e76835e23a64c25", 
        "package_id": "57bcd13709b8ee3f8abb934b"
      }, 
      "build": "py27_0", 
      "build_number": 0, 
      "depends": [
        "bottleneck >=1.0.0", 
        "numpy >=1.9.2", 
        "pandas >=0.16.1", 
        "python 2.7*", 
        "scipy >=0.15.1"
      ], 
      "has_prefix": false, 
      "license": "Apache Software License", 
      "machine": "x86_64", 
      "md5": "51b6a5406a04f30c1770d1d95504b25e", 
      "name": "empyrical", 
      "operatingsystem": "linux", 
      "platform": "linux", 
      "requires": [], 
      "size": 40680, 
      "subdir": "linux-64", 
      "target-triplet": "x86_64-any-linux", 
      "version": "0.2.1"
    }, 
    "empyrical-0.2.1-py34_0.tar.bz2": {
      "arch": "x86_64", 
      "binstar": {
        "channel": "main", 
        "owner_id": "52fa7ff95e76835e23a64c25", 
        "package_id": "57bcd13709b8ee3f8abb934b"
      }, 
      "build": "py34_0", 
      "build_number": 0, 
      "depends": [
        "bottleneck >=1.0.0", 
        "numpy >=1.9.2", 
        "pandas >=0.16.1", 
        "python 3.4*", 
        "scipy >=0.15.1"
      ], 
      "has_prefix": false, 
      "license": "Apache Software License", 
      "machine": "x86_64", 
      "md5": "5a86a317f6d1bed36815b68185168275", 
      "name": "empyrical", 
      "operatingsystem": "linux", 
      "platform": "linux", 
      "requires": [], 
      "size": 41545, 
      "subdir": "linux-64", 
      "target-triplet": "x86_64-any-linux", 
      "version": "0.2.1"
    }, 
    "empyrical-0.2.2-py27_0.tar.bz2": {
      "arch": "x86_64", 
      "binstar": {
        "channel": "main", 
        "owner_id": "52fa7ff95e76835e23a64c25", 
        "package_id": "57bcd13709b8ee3f8abb934b"
      }, 
      "build": "py27_0", 
      "build_number": 0, 
      "depends": [
        "bottleneck >=1.0.0", 
        "numpy >=1.9.2", 
        "pandas >=0.16.1", 
        "python 2.7*", 
        "scipy >=0.15.1"
      ], 
      "has_prefix": false, 
      "license": "Apache Software License", 
      "machine": "x86_64", 
      "md5": "0b01534a43dc7edce3720dd35b38aca3", 
      "name": "empyrical", 
      "operatingsystem": "linux", 
      "platform": "linux", 
      "requires": [], 
      "size": 40271, 
      "subdir": "linux-64", 
      "target-triplet": "x86_64-any-linux", 
      "version": "0.2.2"
    }, 
    "empyrical-0.2.2-py34_0.tar.bz2": {
      "arch": "x86_64", 
      "binstar": {
        "channel": "main", 
        "owner_id": "52fa7ff95e76835e23a64c25", 
        "package_id": "57bcd13709b8ee3f8abb934b"
      }, 
      "build": "py34_0", 
      "build_number": 0, 
      "depends": [
        "bottleneck >=1.0.0", 
        "numpy >=1.9.2", 
        "pandas >=0.16.1", 
        "python 3.4*", 
        "scipy >=0.15.1"
      ], 
      "has_prefix": false, 
      "license": "Apache Software License", 
      "machine": "x86_64", 
      "md5": "299aefe4c6d1ffeea5e8092d4bcf1fe2", 
      "name": "empyrical", 
      "operatingsystem": "linux", 
      "platform": "linux", 
      "requires": [], 
      "size": 41223, 
      "subdir": "linux-64", 
      "target-triplet": "x86_64-any-linux", 
      "version": "0.2.2"
    }, 
    "intervaltree-2.1.0-py27_0.tar.bz2": {
      "arch": "x86_64", 
      "binstar": {
        "channel": "main", 
        "owner_id": "52fa7ff95e76835e23a64c25", 
        "package_id": "5702cc1c4733c36a6cebfd17"
      }, 
      "build": "py27_0", 
      "build_number": 0, 
      "depends": [
        "python 2.7*", 
        "sortedcontainers"
      ], 
      "license": "Apache Software License", 
      "machine": "x86_64", 
      "md5": "8202bc15df453311073896e2c3208717", 
      "name": "intervaltree", 
      "operatingsystem": "linux", 
      "platform": "linux", 
      "requires": [], 
      "size": 46524, 
      "subdir": "linux-64", 
      "target-triplet": "x86_64-any-linux", 
      "version": "2.1.0"
    }, 
    "intervaltree-2.1.0-py34_0.tar.bz2": {
      "arch": "x86_64", 
      "binstar": {
        "channel": "main", 
        "owner_id": "52fa7ff95e76835e23a64c25", 
        "package_id": "5702cc1c4733c36a6cebfd17"
      }, 
      "build": "py34_0", 
      "build_number": 0, 
      "depends": [
        "python 3.4*", 
        "sortedcontainers"
      ], 
      "license": "Apache Software License", 
      "machine": "x86_64", 
      "md5": "2cccf5345c18ab21fab0e58134785cc7", 
      "name": "intervaltree", 
      "operatingsystem": "linux", 
      "platform": "linux", 
      "requires": [], 
      "size": 47296, 
      "subdir": "linux-64", 
      "target-triplet": "x86_64-any-linux", 
      "version": "2.1.0"
    }, 
    "logbook-0.12.5-py27_0.tar.bz2": {
      "arch": "x86_64", 
      "binstar": {
        "channel": "main", 
        "owner_id": "52fa7ff95e76835e23a64c25", 
        "package_id": "5304cbb3e1dad15794468c95"
      }, 
      "build": "py27_0", 
      "build_number": 0, 
      "depends": [
        "python 2.7*"
      ], 
      "license": "BSD", 
      "machine": "x86_64", 
      "md5": "48380cd428afe13b8175f1b63e89fc4a", 
      "name": "logbook", 
      "operatingsystem": "linux", 
      "platform": "linux", 
      "requires": [], 
      "size": 211960, 
      "subdir": "linux-64", 
      "target-triplet": "x86_64-any-linux", 
      "version": "0.12.5"
    }, 
    "logbook-0.12.5-py34_0.tar.bz2": {
      "arch": "x86_64", 
      "binstar": {
        "channel": "main", 
        "owner_id": "52fa7ff95e76835e23a64c25", 
        "package_id": "5304cbb3e1dad15794468c95"
      }, 
      "build": "py34_0", 
      "build_number": 0, 
      "depends": [
        "python 3.4*"
      ], 
      "license": "BSD", 
      "machine": "x86_64", 
      "md5": "1ee91d28c62ef24678d14143d4956752", 
      "name": "logbook", 
      "operatingsystem": "linux", 
      "platform": "linux", 
      "requires": [], 
      "size": 238679, 
      "subdir": "linux-64", 
      "target-triplet": "x86_64-any-linux", 
      "version": "0.12.5"
    }, 
    "logbook-0.6.0-py27_0.tar.bz2": {
      "arch": "x86_64", 
      "binstar": {
        "channel": "main", 
        "owner_id": "52fa7ff95e76835e23a64c25", 
        "package_id": "5304cbb3e1dad15794468c95"
      }, 
      "binstar_build": "5.0", 
      "build": "py27_0", 
      "build_number": 0, 
      "depends": [
        "python 2.7*"
      ], 
      "license": "BSD", 
      "machine": "x86_64", 
      "md5": "6c734cddf713ff2c41316d734fb52f66", 
      "name": "logbook", 
      "operatingsystem": "linux", 
      "platform": "linux", 
      "requires": [], 
      "size": 78853, 
      "subdir": "linux-64", 
      "target-triplet": "x86_64-any-linux", 
      "version": "0.6.0"
    }, 
    "logbook-0.6.0-py33_0.tar.bz2": {
      "arch": "x86_64", 
      "binstar": {
        "channel": "main", 
        "owner_id": "52fa7ff95e76835e23a64c25", 
        "package_id": "5304cbb3e1dad15794468c95"
      }, 
      "binstar_build": "5.1", 
      "build": "py33_0", 
      "build_number": 0, 
      "depends": [
        "python 3.3*"
      ], 
      "license": "BSD", 
      "machine": "x86_64", 
      "md5": "bd995faa5d9285b9fb3e443ecbb3cd08", 
      "name": "logbook", 
      "operatingsystem": "linux", 
      "platform": "linux", 
      "requires": [], 
      "size": 81744, 
      "subdir": "linux-64", 
      "target-triplet": "x86_64-any-linux", 
      "version": "0.6.0"
    }, 
    "logbook-0.6.0-py34_0.tar.bz2": {
      "arch": "x86_64", 
      "binstar": {
        "channel": "main", 
        "owner_id": "52fa7ff95e76835e23a64c25", 
        "package_id": "5304cbb3e1dad15794468c95"
      }, 
      "binstar_build": "5.2", 
      "build": "py34_0", 
      "build_number": 0, 
      "depends": [
        "python 3.4*"
      ], 
      "license": "BSD", 
      "machine": "x86_64", 
      "md5": "c85d88c0300ee262eaadb8ea31ced06c", 
      "name": "logbook", 
      "operatingsystem": "linux", 
      "platform": "linux", 
      "requires": [], 
      "size": 81668, 
      "subdir": "linux-64", 
      "target-triplet": "x86_64-any-linux", 
      "version": "0.6.0"
    }, 
    "lru-dict-1.1.4-py27_0.tar.bz2": {
      "arch": "x86_64", 
      "binstar": {
        "channel": "main", 
        "owner_id": "52fa7ff95e76835e23a64c25", 
        "package_id": "57a0b482fe3f5a6f94ca13d0"
      }, 
      "build": "py27_0", 
      "build_number": 0, 
      "depends": [
        "python 2.7*"
      ], 
      "has_prefix": false, 
      "license": "MIT License", 
      "machine": "x86_64", 
      "md5": "fafd8dc3923fe46fed1d7431132ca99c", 
      "name": "lru-dict", 
      "operatingsystem": "linux", 
      "platform": "linux", 
      "requires": [], 
      "size": 20041, 
      "subdir": "linux-64", 
      "target-triplet": "x86_64-any-linux", 
      "version": "1.1.4"
    }, 
    "lru-dict-1.1.4-py34_0.tar.bz2": {
      "arch": "x86_64", 
      "binstar": {
        "channel": "main", 
        "owner_id": "52fa7ff95e76835e23a64c25", 
        "package_id": "57a0b482fe3f5a6f94ca13d0"
      }, 
      "build": "py34_0", 
      "build_number": 0, 
      "depends": [
        "python 3.4*"
      ], 
      "has_prefix": true, 
      "license": "MIT License", 
      "machine": "x86_64", 
      "md5": "47e4f6b3e6c9662a8f31918512a8172d", 
      "name": "lru-dict", 
      "operatingsystem": "linux", 
      "platform": "linux", 
      "requires": [], 
      "size": 18774, 
      "subdir": "linux-64", 
      "target-triplet": "x86_64-any-linux", 
      "version": "1.1.4"
    }, 
    "metautils-0.1.2-py27_0.tar.bz2": {
      "arch": "x86_64", 
      "binstar": {
        "channel": "main", 
        "owner_id": "52fa7ff95e76835e23a64c25", 
        "package_id": "570ed6a8752ed05ba6cc0d78"
      }, 
      "build": "py27_0", 
      "build_number": 0, 
      "depends": [
        "functools32", 
        "python 2.7*"
      ], 
      "license": "Apache Software License", 
      "machine": "x86_64", 
      "md5": "20ba6c7878305bb616c284c401006bd2", 
      "name": "metautils", 
      "operatingsystem": "linux", 
      "platform": "linux", 
      "requires": [], 
      "size": 14180, 
      "subdir": "linux-64", 
      "target-triplet": "x86_64-any-linux", 
      "version": "0.1.2"
    }, 
    "metautils-0.1.2-py34_0.tar.bz2": {
      "arch": "x86_64", 
      "binstar": {
        "channel": "main", 
        "owner_id": "52fa7ff95e76835e23a64c25", 
        "package_id": "570ed6a8752ed05ba6cc0d78"
      }, 
      "build": "py34_0", 
      "build_number": 0, 
      "depends": [
        "python 3.4*"
      ], 
      "license": "Apache Software License", 
      "machine": "x86_64", 
      "md5": "fad4ab0daa683b5bffd090faa37c72b1", 
      "name": "metautils", 
      "operatingsystem": "linux", 
      "platform": "linux", 
      "requires": [], 
      "size": 14895, 
      "subdir": "linux-64", 
      "target-triplet": "x86_64-any-linux", 
      "version": "0.1.2"
    }, 
    "metautils-0.1.2-py35_0.tar.bz2": {
      "arch": "x86_64", 
      "binstar": {
        "channel": "main", 
        "owner_id": "52fa7ff95e76835e23a64c25", 
        "package_id": "570ed6a8752ed05ba6cc0d78"
      }, 
      "build": "py35_0", 
      "build_number": 0, 
      "depends": [
        "python 3.5*"
      ], 
      "license": "Apache Software License", 
      "machine": "x86_64", 
      "md5": "270b25fc4ea3616dcb63adefc3d954c5", 
      "name": "metautils", 
      "operatingsystem": "linux", 
      "platform": "linux", 
      "requires": [], 
      "size": 14854, 
      "subdir": "linux-64", 
      "target-triplet": "x86_64-any-linux", 
      "version": "0.1.2"
    }, 
    "numexpr-2.4.6-np111py27_0.tar.bz2": {
      "arch": "x86_64", 
      "binstar": {
        "channel": "main", 
        "owner_id": "52fa7ff95e76835e23a64c25", 
        "package_id": "56e6b4434428cc5841da5e5c"
      }, 
      "build": "np111py27_0", 
      "build_number": 0, 
      "depends": [
        "numpy 1.11*", 
        "python 2.7*"
      ], 
      "has_prefix": true, 
      "machine": "x86_64", 
      "md5": "7a43aeba48fdba20513c321c586a03b7", 
      "name": "numexpr", 
      "operatingsystem": "linux", 
      "platform": "linux", 
      "requires": [], 
      "size": 326311, 
      "subdir": "linux-64", 
      "target-triplet": "x86_64-any-linux", 
      "version": "2.4.6"
    }, 
    "numexpr-2.4.6-np111py34_0.tar.bz2": {
      "arch": "x86_64", 
      "binstar": {
        "channel": "main", 
        "owner_id": "52fa7ff95e76835e23a64c25", 
        "package_id": "56e6b4434428cc5841da5e5c"
      }, 
      "build": "np111py34_0", 
      "build_number": 0, 
      "depends": [
        "numpy 1.11*", 
        "python 3.4*"
      ], 
      "has_prefix": true, 
      "machine": "x86_64", 
      "md5": "06d1f1b9361981466c725be1335c4f72", 
      "name": "numexpr", 
      "operatingsystem": "linux", 
      "platform": "linux", 
      "requires": [], 
      "size": 352215, 
      "subdir": "linux-64", 
      "target-triplet": "x86_64-any-linux", 
      "version": "2.4.6"
    }, 
    "numexpr-2.4.6-np19py27_0.tar.bz2": {
      "arch": "x86_64", 
      "binstar": {
        "channel": "main", 
        "owner_id": "52fa7ff95e76835e23a64c25", 
        "package_id": "56e6b4434428cc5841da5e5c"
      }, 
      "build": "np19py27_0", 
      "build_number": 0, 
      "depends": [
        "numpy 1.9*", 
        "python 2.7*"
      ], 
      "machine": "x86_64", 
      "md5": "2871501c3b01cfdc8ad4cc299de20bef", 
      "name": "numexpr", 
      "operatingsystem": "linux", 
      "platform": "linux", 
      "requires": [], 
      "size": 329528, 
      "subdir": "linux-64", 
      "target-triplet": "x86_64-any-linux", 
      "version": "2.4.6"
    }, 
    "numexpr-2.4.6-np19py34_0.tar.bz2": {
      "arch": "x86_64", 
      "binstar": {
        "channel": "main", 
        "owner_id": "52fa7ff95e76835e23a64c25", 
        "package_id": "56e6b4434428cc5841da5e5c"
      }, 
      "build": "np19py34_0", 
      "build_number": 0, 
      "depends": [
        "numpy 1.9*", 
        "python 3.4*"
      ], 
      "machine": "x86_64", 
      "md5": "4ebd60258b5837333d012d034f24b6e1", 
      "name": "numexpr", 
      "operatingsystem": "linux", 
      "platform": "linux", 
      "requires": [], 
      "size": 358240, 
      "subdir": "linux-64", 
      "target-triplet": "x86_64-any-linux", 
      "version": "2.4.6"
    }, 
    "setuptools_scm-1.10.1-py27_0.tar.bz2": {
      "arch": "x86_64", 
      "binstar": {
        "channel": "main", 
        "owner_id": "52fa7ff95e76835e23a64c25", 
        "package_id": "56cd402d266fe472207cfe4a"
      }, 
      "build": "py27_0", 
      "build_number": 0, 
      "depends": [
        "python 2.7*", 
        "setuptools"
      ], 
      "license": "MIT License", 
      "machine": "x86_64", 
      "md5": "fd5d8c94359ba489aaaf59428fc37d76", 
      "name": "setuptools_scm", 
      "operatingsystem": "linux", 
      "platform": "linux", 
      "requires": [], 
      "size": 23002, 
      "subdir": "linux-64", 
      "target-triplet": "x86_64-any-linux", 
      "version": "1.10.1"
    }, 
    "setuptools_scm-1.10.1-py34_0.tar.bz2": {
      "arch": "x86_64", 
      "binstar": {
        "channel": "main", 
        "owner_id": "52fa7ff95e76835e23a64c25", 
        "package_id": "56cd402d266fe472207cfe4a"
      }, 
      "build": "py34_0", 
      "build_number": 0, 
      "depends": [
        "python 3.4*", 
        "setuptools"
      ], 
      "license": "MIT License", 
      "machine": "x86_64", 
      "md5": "1a870f159e6623349116c2ac98d003f9", 
      "name": "setuptools_scm", 
      "operatingsystem": "linux", 
      "platform": "linux", 
      "requires": [], 
      "size": 23129, 
      "subdir": "linux-64", 
      "target-triplet": "x86_64-any-linux", 
      "version": "1.10.1"
    }, 
    "sortedcontainers-1.4.4-py27_0.tar.bz2": {
      "arch": "x86_64", 
      "binstar": {
        "channel": "main", 
        "owner_id": "52fa7ff95e76835e23a64c25", 
        "package_id": "5702cc050697b672acb82587"
      }, 
      "build": "py27_0", 
      "build_number": 0, 
      "depends": [
        "python 2.7*"
      ], 
      "license": "Apache Software License", 
      "machine": "x86_64", 
      "md5": "eeb8f3b4b9cce81fa9dd9389fb4ecfb9", 
      "name": "sortedcontainers", 
      "operatingsystem": "linux", 
      "platform": "linux", 
      "requires": [], 
      "size": 62259, 
      "subdir": "linux-64", 
      "target-triplet": "x86_64-any-linux", 
      "version": "1.4.4"
    }, 
    "sortedcontainers-1.4.4-py34_0.tar.bz2": {
      "arch": "x86_64", 
      "binstar": {
        "channel": "main", 
        "owner_id": "52fa7ff95e76835e23a64c25", 
        "package_id": "5702cc050697b672acb82587"
      }, 
      "build": "py34_0", 
      "build_number": 0, 
      "depends": [
        "python 3.4*"
      ], 
      "license": "Apache Software License", 
      "machine": "x86_64", 
      "md5": "c6251643b0cf0911228afecc480a7961", 
      "name": "sortedcontainers", 
      "operatingsystem": "linux", 
      "platform": "linux", 
      "requires": [], 
      "size": 63242, 
      "subdir": "linux-64", 
      "target-triplet": "x86_64-any-linux", 
      "version": "1.4.4"
    }, 
    "ta-lib-0.4.8-np110py27_0.tar.bz2": {
      "arch": "x86_64", 
      "binstar": {
        "channel": "main", 
        "owner_id": "52fa7ff95e76835e23a64c25", 
        "package_id": "530511ac5e76835e24c02373"
      }, 
      "build": "np110py27_0", 
      "build_number": 0, 
      "depends": [
        "numpy 1.10*", 
        "python 2.7*"
      ], 
      "license": "BSD License", 
      "machine": "x86_64", 
      "md5": "fe91feb48ec4957c947b77320b66f1d7", 
      "name": "ta-lib", 
      "operatingsystem": "linux", 
      "platform": "linux", 
      "requires": [], 
      "size": 2722769, 
      "subdir": "linux-64", 
      "target-triplet": "x86_64-any-linux", 
      "version": "0.4.8"
    }, 
    "ta-lib-0.4.8-np110py34_0.tar.bz2": {
      "arch": "x86_64", 
      "binstar": {
        "channel": "main", 
        "owner_id": "52fa7ff95e76835e23a64c25", 
        "package_id": "530511ac5e76835e24c02373"
      }, 
      "build": "np110py34_0", 
      "build_number": 0, 
      "depends": [
        "numpy 1.10*", 
        "python 3.4*"
      ], 
      "license": "BSD License", 
      "machine": "x86_64", 
      "md5": "a5f4c0aedb66cd94dbb66e2491cadb1a", 
      "name": "ta-lib", 
      "operatingsystem": "linux", 
      "platform": "linux", 
      "requires": [], 
      "size": 2822093, 
      "subdir": "linux-64", 
      "target-triplet": "x86_64-any-linux", 
      "version": "0.4.8"
    }, 
    "ta-lib-0.4.8-np18py27_0.tar.bz2": {
      "arch": "x86_64", 
      "binstar": {
        "channel": "main", 
        "owner_id": "52fa7ff95e76835e23a64c25", 
        "package_id": "530511ac5e76835e24c02373"
      }, 
      "build": "np18py27_0", 
      "build_number": 0, 
      "depends": [
        "numpy 1.8*", 
        "python 2.7*"
      ], 
      "home_page": "http://github.com/mrjbq7/ta-lib", 
      "license": "BSD License", 
      "md5": "c1fd88b72eee8b899a50b518ffe9f7d2", 
      "name": "ta-lib", 
      "platform": "linux", 
      "requires": [], 
      "size": 2313311, 
      "version": "0.4.8"
    }, 
    "ta-lib-0.4.8-np18py33_0.tar.bz2": {
      "arch": "x86_64", 
      "binstar": {
        "channel": "main", 
        "owner_id": "52fa7ff95e76835e23a64c25", 
        "package_id": "530511ac5e76835e24c02373"
      }, 
      "build": "np18py33_0", 
      "build_number": 0, 
      "depends": [
        "numpy 1.8*", 
        "python 3.3*"
      ], 
      "home_page": "http://github.com/mrjbq7/ta-lib", 
      "license": "BSD License", 
      "md5": "6781f69aa6323fae60e806c821a71f91", 
      "name": "ta-lib", 
      "platform": "linux", 
      "requires": [], 
      "size": 2441628, 
      "version": "0.4.8"
    }, 
    "ta-lib-0.4.8-np19py27_0.tar.bz2": {
      "arch": "x86_64", 
      "binstar": {
        "channel": "main", 
        "owner_id": "52fa7ff95e76835e23a64c25", 
        "package_id": "530511ac5e76835e24c02373"
      }, 
      "build": "np19py27_0", 
      "build_number": 0, 
      "depends": [
        "numpy 1.9*", 
        "python 2.7*"
      ], 
      "license": "BSD License", 
      "machine": "x86_64", 
      "md5": "1781a1989a325da5d6afa85f673e8b06", 
      "name": "ta-lib", 
      "operatingsystem": "linux", 
      "platform": "linux", 
      "requires": [], 
      "size": 2721310, 
      "subdir": "linux-64", 
      "target-triplet": "x86_64-any-linux", 
      "version": "0.4.8"
    }, 
    "ta-lib-0.4.8-np19py33_0.tar.bz2": {
      "arch": "x86_64", 
      "binstar": {
        "channel": "main", 
        "owner_id": "52fa7ff95e76835e23a64c25", 
        "package_id": "530511ac5e76835e24c02373"
      }, 
      "build": "np19py33_0", 
      "build_number": 0, 
      "depends": [
        "numpy 1.9*", 
        "python 3.3*"
      ], 
      "home_page": "http://github.com/mrjbq7/ta-lib", 
      "license": "BSD License", 
      "md5": "aa4118bfd881d2729c4357492302772b", 
      "name": "ta-lib", 
      "platform": "linux", 
      "requires": [], 
      "size": 2442268, 
      "version": "0.4.8"
    }, 
    "ta-lib-0.4.8-np19py34_0.tar.bz2": {
      "arch": "x86_64", 
      "binstar": {
        "channel": "main", 
        "owner_id": "52fa7ff95e76835e23a64c25", 
        "package_id": "530511ac5e76835e24c02373"
      }, 
      "build": "np19py34_0", 
      "build_number": 0, 
      "depends": [
        "numpy 1.9*", 
        "python 3.4*"
      ], 
      "license": "BSD License", 
      "machine": "x86_64", 
      "md5": "0e3ff67db2b7767de46d2545a7a37612", 
      "name": "ta-lib", 
      "operatingsystem": "linux", 
      "platform": "linux", 
      "requires": [], 
      "size": 2821919, 
      "subdir": "linux-64", 
      "target-triplet": "x86_64-any-linux", 
      "version": "0.4.8"
    }, 
    "ta-lib-0.4.9-np110py27_0.tar.bz2": {
      "arch": "x86_64", 
      "binstar": {
        "channel": "main", 
        "owner_id": "52fa7ff95e76835e23a64c25", 
        "package_id": "530511ac5e76835e24c02373"
      }, 
      "build": "np110py27_0", 
      "build_number": 0, 
      "depends": [
        "numpy 1.10*", 
        "python 2.7*"
      ], 
      "license": "BSD License", 
      "machine": "x86_64", 
      "md5": "490e9482ebc55c591a68382d9f26ed80", 
      "name": "ta-lib", 
      "operatingsystem": "linux", 
      "platform": "linux", 
      "requires": [], 
      "size": 2750932, 
      "subdir": "linux-64", 
      "target-triplet": "x86_64-any-linux", 
      "version": "0.4.9"
    }, 
    "ta-lib-0.4.9-np110py34_0.tar.bz2": {
      "arch": "x86_64", 
      "binstar": {
        "channel": "main", 
        "owner_id": "52fa7ff95e76835e23a64c25", 
        "package_id": "530511ac5e76835e24c02373"
      }, 
      "build": "np110py34_0", 
      "build_number": 0, 
      "depends": [
        "numpy 1.10*", 
        "python 3.4*"
      ], 
      "license": "BSD License", 
      "machine": "x86_64", 
      "md5": "34c3a09a5d59b8967508c407ccde90b4", 
      "name": "ta-lib", 
      "operatingsystem": "linux", 
      "platform": "linux", 
      "requires": [], 
      "size": 2869861, 
      "subdir": "linux-64", 
      "target-triplet": "x86_64-any-linux", 
      "version": "0.4.9"
    }, 
    "ta-lib-0.4.9-np111py27_0.tar.bz2": {
      "arch": "x86_64", 
      "binstar": {
        "channel": "main", 
        "owner_id": "52fa7ff95e76835e23a64c25", 
        "package_id": "530511ac5e76835e24c02373"
      }, 
      "build": "np111py27_0", 
      "build_number": 0, 
      "depends": [
        "numpy 1.11*", 
        "python 2.7*"
      ], 
      "license": "BSD License", 
      "machine": "x86_64", 
      "md5": "3d47250ad172e83785fd0704a3cd500f", 
      "name": "ta-lib", 
      "operatingsystem": "linux", 
      "platform": "linux", 
      "requires": [], 
      "size": 2767067, 
      "subdir": "linux-64", 
      "target-triplet": "x86_64-any-linux", 
      "version": "0.4.9"
    }, 
    "ta-lib-0.4.9-np111py34_0.tar.bz2": {
      "arch": "x86_64", 
      "binstar": {
        "channel": "main", 
        "owner_id": "52fa7ff95e76835e23a64c25", 
        "package_id": "530511ac5e76835e24c02373"
      }, 
      "build": "np111py34_0", 
      "build_number": 0, 
      "depends": [
        "numpy 1.11*", 
        "python 3.4*"
      ], 
      "license": "BSD License", 
      "machine": "x86_64", 
      "md5": "a08ce985b27cf701ca3948afb74678f2", 
      "name": "ta-lib", 
      "operatingsystem": "linux", 
      "platform": "linux", 
      "requires": [], 
      "size": 2931700, 
      "subdir": "linux-64", 
      "target-triplet": "x86_64-any-linux", 
      "version": "0.4.9"
    }, 
    "ta-lib-0.4.9-np111py35_0.tar.bz2": {
      "arch": "x86_64", 
      "binstar": {
        "channel": "main", 
        "owner_id": "52fa7ff95e76835e23a64c25", 
        "package_id": "530511ac5e76835e24c02373"
      }, 
      "build": "np111py35_0", 
      "build_number": 0, 
      "depends": [
        "numpy 1.11*", 
        "python 3.5*"
      ], 
      "has_prefix": true, 
      "license": "BSD License", 
      "machine": "x86_64", 
      "md5": "8c93b1f913ce7eb945513c7d1557d011", 
      "name": "ta-lib", 
      "operatingsystem": "linux", 
      "platform": "linux", 
      "requires": [], 
      "size": 2544867, 
      "subdir": "linux-64", 
      "target-triplet": "x86_64-any-linux", 
      "version": "0.4.9"
    }, 
    "ta-lib-0.4.9-np19py27_0.tar.bz2": {
      "arch": "x86_64", 
      "binstar": {
        "channel": "main", 
        "owner_id": "52fa7ff95e76835e23a64c25", 
        "package_id": "530511ac5e76835e24c02373"
      }, 
      "build": "np19py27_0", 
      "build_number": 0, 
      "depends": [
        "numpy 1.9*", 
        "python 2.7*"
      ], 
      "license": "BSD License", 
      "machine": "x86_64", 
      "md5": "15d5d6b879fe411d3a218e0c8b704cc8", 
      "name": "ta-lib", 
      "operatingsystem": "linux", 
      "platform": "linux", 
      "requires": [], 
      "size": 2424699, 
      "subdir": "linux-64", 
      "target-triplet": "x86_64-any-linux", 
      "version": "0.4.9"
    }, 
    "ta-lib-0.4.9-np19py34_0.tar.bz2": {
      "arch": "x86_64", 
      "binstar": {
        "channel": "main", 
        "owner_id": "52fa7ff95e76835e23a64c25", 
        "package_id": "530511ac5e76835e24c02373"
      }, 
      "build": "np19py34_0", 
      "build_number": 0, 
      "depends": [
        "numpy 1.9*", 
        "python 3.4*"
      ], 
      "license": "BSD License", 
      "machine": "x86_64", 
      "md5": "ffbadcb17d5c3ee43d23833e765bd133", 
      "name": "ta-lib", 
      "operatingsystem": "linux", 
      "platform": "linux", 
      "requires": [], 
      "size": 2609332, 
      "subdir": "linux-64", 
      "target-triplet": "x86_64-any-linux", 
      "version": "0.4.9"
    }, 
    "zipline-0.6.0-np18py27_0.tar.bz2": {
      "arch": "x86_64", 
      "binstar": {
        "channel": "main", 
        "owner_id": "52fa7ff95e76835e23a64c25", 
        "package_id": "53051f135e76835e253b1310"
      }, 
      "build": "np18py27_0", 
      "build_number": 0, 
      "depends": [
        "logbook", 
        "matplotlib", 
        "numpy 1.8*", 
        "pandas", 
        "python 2.7*", 
        "pytz", 
        "requests", 
        "scipy", 
        "ta-lib"
      ], 
      "home_page": "https://github.com/quantopian/zipline", 
      "license": "Apache Software License", 
      "md5": "38dd942341a2faf5e14490bc5fe7ebcf", 
      "name": "zipline", 
      "platform": "linux", 
      "requires": [], 
      "size": 176677, 
      "version": "0.6.0"
    }, 
    "zipline-0.6.1-np17_0.tar.bz2": {
      "arch": "x86_64", 
      "binstar": {
        "channel": "main", 
        "owner_id": "52fa7ff95e76835e23a64c25", 
        "package_id": "53051f135e76835e253b1310"
      }, 
      "build": "np17_0", 
      "build_number": 0, 
      "depends": [
        "logbook", 
        "matplotlib", 
        "numpy 1.7*", 
        "pandas", 
        "pytz", 
        "requests", 
        "scipy", 
        "ta-lib"
      ], 
      "home_page": "https://github.com/quantopian/zipline", 
      "license": "Apache Software License", 
      "md5": "e4d79c05618a3d87e28f6967b7280ad8", 
      "name": "zipline", 
      "platform": "linux", 
      "requires": [], 
      "size": 213173, 
      "version": "0.6.1"
    }, 
    "zipline-0.7.0-np18py27_0.tar.bz2": {
      "arch": "x86_64", 
      "binstar": {
        "channel": "main", 
        "owner_id": "52fa7ff95e76835e23a64c25", 
        "package_id": "53051f135e76835e253b1310"
      }, 
      "build": "np18py27_0", 
      "build_number": 0, 
      "depends": [
        "logbook", 
        "matplotlib", 
        "numpy 1.8*", 
        "pandas", 
        "python 2.7*", 
        "pytz", 
        "requests", 
        "scipy", 
        "ta-lib"
      ], 
      "home_page": "https://github.com/quantopian/zipline", 
      "license": "Apache Software License", 
      "md5": "b8b00f413c4aae591373eb64c12cb4d7", 
      "name": "zipline", 
      "platform": "linux", 
      "requires": [], 
      "size": 246316, 
      "version": "0.7.0"
    }, 
    "zipline-0.7.0-np18py33_0.tar.bz2": {
      "arch": "x86_64", 
      "binstar": {
        "channel": "main", 
        "owner_id": "52fa7ff95e76835e23a64c25", 
        "package_id": "53051f135e76835e253b1310"
      }, 
      "build": "np18py33_0", 
      "build_number": 0, 
      "depends": [
        "logbook", 
        "matplotlib", 
        "numpy 1.8*", 
        "pandas", 
        "python 3.3*", 
        "pytz", 
        "requests", 
        "scipy", 
        "ta-lib"
      ], 
      "home_page": "https://github.com/quantopian/zipline", 
      "license": "Apache Software License", 
      "md5": "d6303b4b8c0c07ac3b2313389e30407f", 
      "name": "zipline", 
      "platform": "linux", 
      "requires": [], 
      "size": 258274, 
      "version": "0.7.0"
    }, 
    "zipline-0.7.0-np19py27_0.tar.bz2": {
      "arch": "x86_64", 
      "binstar": {
        "channel": "main", 
        "owner_id": "52fa7ff95e76835e23a64c25", 
        "package_id": "53051f135e76835e253b1310"
      }, 
      "build": "np19py27_0", 
      "build_number": 0, 
      "depends": [
        "logbook", 
        "matplotlib", 
        "numpy 1.9*", 
        "pandas", 
        "python 2.7*", 
        "pytz", 
        "requests", 
        "scipy"
      ], 
      "license": "Apache Software License", 
      "machine": "x86_64", 
      "md5": "7e602647b36ddefc4c999e76351447a3", 
      "name": "zipline", 
      "operatingsystem": "linux", 
      "platform": "linux", 
      "requires": [], 
      "size": 246236, 
      "target-triplet": "x86_64-any-linux", 
      "version": "0.7.0"
    }, 
    "zipline-0.7.0-np19py33_0.tar.bz2": {
      "arch": "x86_64", 
      "binstar": {
        "channel": "main", 
        "owner_id": "52fa7ff95e76835e23a64c25", 
        "package_id": "53051f135e76835e253b1310"
      }, 
      "build": "np19py33_0", 
      "build_number": 0, 
      "depends": [
        "logbook", 
        "matplotlib", 
        "numpy 1.9*", 
        "pandas", 
        "python 3.3*", 
        "pytz", 
        "requests", 
        "scipy"
      ], 
      "license": "Apache Software License", 
      "machine": "x86_64", 
      "md5": "15a25ecb991ea3b258c73928160d8079", 
      "name": "zipline", 
      "operatingsystem": "linux", 
      "platform": "linux", 
      "requires": [], 
      "size": 258098, 
      "target-triplet": "x86_64-any-linux", 
      "version": "0.7.0"
    }, 
    "zipline-0.7.0rc1-np18_0.tar.bz2": {
      "arch": "x86_64", 
      "binstar": {
        "channel": "main", 
        "owner_id": "52fa7ff95e76835e23a64c25", 
        "package_id": "53051f135e76835e253b1310"
      }, 
      "build": "np18_0", 
      "build_number": 0, 
      "depends": [
        "logbook", 
        "matplotlib", 
        "numpy 1.8*", 
        "pandas", 
        "pytz", 
        "requests", 
        "scipy", 
        "ta-lib"
      ], 
      "home_page": "https://github.com/quantopian/zipline", 
      "license": "Apache Software License", 
      "md5": "ab5e948cf9cc330cd428d636f1bf9e1c", 
      "name": "zipline", 
      "platform": "linux", 
      "requires": [], 
      "size": 242141, 
      "version": "0.7.0rc1"
    }, 
    "zipline-0.7.0rc1-np18py27_0.tar.bz2": {
      "arch": "x86_64", 
      "binstar": {
        "channel": "main", 
        "owner_id": "52fa7ff95e76835e23a64c25", 
        "package_id": "53051f135e76835e253b1310"
      }, 
      "build": "np18py27_0", 
      "build_number": 0, 
      "depends": [
        "logbook", 
        "matplotlib", 
        "numpy 1.8*", 
        "pandas", 
        "python 2.7*", 
        "pytz", 
        "requests", 
        "scipy", 
        "ta-lib"
      ], 
      "home_page": "https://github.com/quantopian/zipline", 
      "license": "Apache Software License", 
      "md5": "543e639e1a32271f539a7b9b175f4cc6", 
      "name": "zipline", 
      "platform": "linux", 
      "requires": [], 
      "size": 242124, 
      "version": "0.7.0rc1"
    }, 
    "zipline-0.7.0rc1-np18py33_0.tar.bz2": {
      "arch": "x86_64", 
      "binstar": {
        "channel": "main", 
        "owner_id": "52fa7ff95e76835e23a64c25", 
        "package_id": "53051f135e76835e253b1310"
      }, 
      "build": "np18py33_0", 
      "build_number": 0, 
      "depends": [
        "logbook", 
        "matplotlib", 
        "numpy 1.8*", 
        "pandas", 
        "python 3.3*", 
        "pytz", 
        "requests", 
        "scipy", 
        "ta-lib"
      ], 
      "home_page": "https://github.com/quantopian/zipline", 
      "license": "Apache Software License", 
      "md5": "d9fcf965172a9da7b7424529fffd2e85", 
      "name": "zipline", 
      "platform": "linux", 
      "requires": [], 
      "size": 253506, 
      "version": "0.7.0rc1"
    }, 
    "zipline-0.8.4-np110py27_0.tar.bz2": {
      "arch": "x86_64", 
      "binstar": {
        "channel": "main", 
        "owner_id": "52fa7ff95e76835e23a64c25", 
        "package_id": "53051f135e76835e253b1310"
      }, 
      "build": "np110py27_0", 
      "build_number": 0, 
      "depends": [
        "bcolz >=0.12.1", 
        "bottleneck >=1.0.0", 
        "click >=4.0.0", 
        "contextlib2 >=0.4.0", 
        "cyordereddict >=0.2.2", 
        "cython >=0.22.1", 
        "decorator >=4.0.0", 
        "logbook >=0.12.5", 
        "networkx >=1.9.1", 
        "numexpr >=2.4.3", 
        "numpy 1.10*", 
        "pandas >=0.16.1", 
        "patsy >=0.4.0", 
        "pip >=7.1.0", 
        "python 2.7*", 
        "python-dateutil >=2.4.2", 
        "pytz >=2015.4", 
        "requests >=2.9.1", 
        "scipy >=0.15.1", 
        "setuptools >18.0", 
        "six >=1.9.0", 
        "sqlalchemy >=1.0.8", 
        "statsmodels >=0.6.1", 
        "toolz >=0.7.4"
      ], 
      "license": "Apache Software License", 
      "machine": "x86_64", 
      "md5": "9f909fd01030ff73826a5d11e6ee41b4", 
      "name": "zipline", 
      "operatingsystem": "linux", 
      "platform": "linux", 
      "requires": [], 
      "size": 2099194, 
      "subdir": "linux-64", 
      "target-triplet": "x86_64-any-linux", 
      "version": "0.8.4"
    }, 
    "zipline-0.8.4-np110py34_0.tar.bz2": {
      "arch": "x86_64", 
      "binstar": {
        "channel": "main", 
        "owner_id": "52fa7ff95e76835e23a64c25", 
        "package_id": "53051f135e76835e253b1310"
      }, 
      "build": "np110py34_0", 
      "build_number": 0, 
      "depends": [
        "bcolz >=0.12.1", 
        "bottleneck >=1.0.0", 
        "click >=4.0.0", 
        "contextlib2 >=0.4.0", 
        "cyordereddict >=0.2.2", 
        "cython >=0.22.1", 
        "decorator >=4.0.0", 
        "logbook >=0.12.5", 
        "networkx >=1.9.1", 
        "numexpr >=2.4.3", 
        "numpy 1.10*", 
        "pandas >=0.16.1", 
        "patsy >=0.4.0", 
        "pip >=7.1.0", 
        "python 3.4*", 
        "python-dateutil >=2.4.2", 
        "pytz >=2015.4", 
        "requests >=2.9.1", 
        "scipy >=0.15.1", 
        "setuptools >18.0", 
        "six >=1.9.0", 
        "sqlalchemy >=1.0.8", 
        "statsmodels >=0.6.1", 
        "toolz >=0.7.4"
      ], 
      "license": "Apache Software License", 
      "machine": "x86_64", 
      "md5": "61ca77846d686663d5d15ba17d76ee67", 
      "name": "zipline", 
      "operatingsystem": "linux", 
      "platform": "linux", 
      "requires": [], 
      "size": 2105885, 
      "subdir": "linux-64", 
      "target-triplet": "x86_64-any-linux", 
      "version": "0.8.4"
    }, 
    "zipline-0.8.4-np19py27_0.tar.bz2": {
      "arch": "x86_64", 
      "binstar": {
        "channel": "main", 
        "owner_id": "52fa7ff95e76835e23a64c25", 
        "package_id": "53051f135e76835e253b1310"
      }, 
      "build": "np19py27_0", 
      "build_number": 0, 
      "depends": [
        "bcolz >=0.12.1", 
        "bottleneck >=1.0.0", 
        "click >=4.0.0", 
        "contextlib2 >=0.4.0", 
        "cyordereddict >=0.2.2", 
        "cython >=0.22.1", 
        "decorator >=4.0.0", 
        "logbook >=0.12.5", 
        "networkx >=1.9.1", 
        "numexpr >=2.4.3", 
        "numpy 1.9*", 
        "pandas >=0.16.1", 
        "patsy >=0.4.0", 
        "pip >=7.1.0", 
        "python 2.7*", 
        "python-dateutil >=2.4.2", 
        "pytz >=2015.4", 
        "requests >=2.9.1", 
        "scipy >=0.15.1", 
        "setuptools >18.0", 
        "six >=1.9.0", 
        "sqlalchemy >=1.0.8", 
        "statsmodels >=0.6.1", 
        "toolz >=0.7.4"
      ], 
      "license": "Apache Software License", 
      "machine": "x86_64", 
      "md5": "4349db7b8c9bb4025042adf18341416d", 
      "name": "zipline", 
      "operatingsystem": "linux", 
      "platform": "linux", 
      "requires": [], 
      "size": 2100169, 
      "subdir": "linux-64", 
      "target-triplet": "x86_64-any-linux", 
      "version": "0.8.4"
    }, 
    "zipline-0.8.4-np19py34_0.tar.bz2": {
      "arch": "x86_64", 
      "binstar": {
        "channel": "main", 
        "owner_id": "52fa7ff95e76835e23a64c25", 
        "package_id": "53051f135e76835e253b1310"
      }, 
      "build": "np19py34_0", 
      "build_number": 0, 
      "depends": [
        "bcolz >=0.12.1", 
        "bottleneck >=1.0.0", 
        "click >=4.0.0", 
        "contextlib2 >=0.4.0", 
        "cyordereddict >=0.2.2", 
        "cython >=0.22.1", 
        "decorator >=4.0.0", 
        "logbook >=0.12.5", 
        "networkx >=1.9.1", 
        "numexpr >=2.4.3", 
        "numpy 1.9*", 
        "pandas >=0.16.1", 
        "patsy >=0.4.0", 
        "pip >=7.1.0", 
        "python 3.4*", 
        "python-dateutil >=2.4.2", 
        "pytz >=2015.4", 
        "requests >=2.9.1", 
        "scipy >=0.15.1", 
        "setuptools >18.0", 
        "six >=1.9.0", 
        "sqlalchemy >=1.0.8", 
        "statsmodels >=0.6.1", 
        "toolz >=0.7.4"
      ], 
      "license": "Apache Software License", 
      "machine": "x86_64", 
      "md5": "f36cdd216594da4f5707724524ad95fa", 
      "name": "zipline", 
      "operatingsystem": "linux", 
      "platform": "linux", 
      "requires": [], 
      "size": 2106595, 
      "subdir": "linux-64", 
      "target-triplet": "x86_64-any-linux", 
      "version": "0.8.4"
    }, 
    "zipline-0.9.0-np110py27_0.tar.bz2": {
      "arch": "x86_64", 
      "binstar": {
        "channel": "main", 
        "owner_id": "52fa7ff95e76835e23a64c25", 
        "package_id": "53051f135e76835e253b1310"
      }, 
      "build": "np110py27_0", 
      "build_number": 0, 
      "depends": [
        "bcolz >=0.12.1", 
        "bottleneck >=1.0.0", 
        "click >=4.0.0", 
        "contextlib2 >=0.4.0", 
        "cyordereddict >=0.2.2", 
        "cython >=0.22.1", 
        "decorator >=4.0.0", 
        "logbook >=0.12.5", 
        "networkx >=1.9.1", 
        "numexpr >=2.4.6", 
        "numpy 1.10*", 
        "pandas >=0.17.1", 
        "patsy >=0.4.0", 
        "pip >=7.1.0", 
        "python 2.7*", 
        "python-dateutil >=2.4.2", 
        "pytz >=2015.4", 
        "requests >=2.9.1", 
        "scipy >=0.16.1", 
        "setuptools >18.0", 
        "six >=1.10.0", 
        "sqlalchemy >=1.0.8", 
        "statsmodels >=0.6.1", 
        "toolz >=0.7.4"
      ], 
      "license": "Apache Software License", 
      "machine": "x86_64", 
      "md5": "de79be1266452e2a469a32f80e3a00c7", 
      "name": "zipline", 
      "operatingsystem": "linux", 
      "platform": "linux", 
      "requires": [], 
      "size": 1943750, 
      "subdir": "linux-64", 
      "target-triplet": "x86_64-any-linux", 
      "version": "0.9.0"
    }, 
    "zipline-0.9.0-np110py34_0.tar.bz2": {
      "arch": "x86_64", 
      "binstar": {
        "channel": "main", 
        "owner_id": "52fa7ff95e76835e23a64c25", 
        "package_id": "53051f135e76835e253b1310"
      }, 
      "build": "np110py34_0", 
      "build_number": 0, 
      "depends": [
        "bcolz >=0.12.1", 
        "bottleneck >=1.0.0", 
        "click >=4.0.0", 
        "contextlib2 >=0.4.0", 
        "cyordereddict >=0.2.2", 
        "cython >=0.22.1", 
        "decorator >=4.0.0", 
        "logbook >=0.12.5", 
        "networkx >=1.9.1", 
        "numexpr >=2.4.6", 
        "numpy 1.10*", 
        "pandas >=0.17.1", 
        "patsy >=0.4.0", 
        "pip >=7.1.0", 
        "python 3.4*", 
        "python-dateutil >=2.4.2", 
        "pytz >=2015.4", 
        "requests >=2.9.1", 
        "scipy >=0.16.1", 
        "setuptools >18.0", 
        "six >=1.10.0", 
        "sqlalchemy >=1.0.8", 
        "statsmodels >=0.6.1", 
        "toolz >=0.7.4"
      ], 
      "license": "Apache Software License", 
      "machine": "x86_64", 
      "md5": "82c95af7b26aa36168aaaf359abdad95", 
      "name": "zipline", 
      "operatingsystem": "linux", 
      "platform": "linux", 
      "requires": [], 
      "size": 2029942, 
      "subdir": "linux-64", 
      "target-triplet": "x86_64-any-linux", 
      "version": "0.9.0"
    }, 
    "zipline-0.9.0-np19py27_0.tar.bz2": {
      "arch": "x86_64", 
      "binstar": {
        "channel": "main", 
        "owner_id": "52fa7ff95e76835e23a64c25", 
        "package_id": "53051f135e76835e253b1310"
      }, 
      "build": "np19py27_0", 
      "build_number": 0, 
      "depends": [
        "bcolz >=0.12.1", 
        "bottleneck >=1.0.0", 
        "click >=4.0.0", 
        "contextlib2 >=0.4.0", 
        "cyordereddict >=0.2.2", 
        "cython >=0.22.1", 
        "decorator >=4.0.0", 
        "logbook >=0.12.5", 
        "networkx >=1.9.1", 
        "numexpr >=2.4.6", 
        "numpy 1.9*", 
        "pandas >=0.16.1", 
        "patsy >=0.4.0", 
        "pip >=7.1.0", 
        "python 2.7*", 
        "python-dateutil >=2.4.2", 
        "pytz >=2015.4", 
        "requests >=2.9.1", 
        "scipy >=0.15.1", 
        "setuptools >18.0", 
        "six >=1.10.0", 
        "sqlalchemy >=1.0.8", 
        "statsmodels >=0.6.1", 
        "toolz >=0.7.4"
      ], 
      "license": "Apache Software License", 
      "machine": "x86_64", 
      "md5": "e45c11614db76853771c5c7d20b314d4", 
      "name": "zipline", 
      "operatingsystem": "linux", 
      "platform": "linux", 
      "requires": [], 
      "size": 1944237, 
      "subdir": "linux-64", 
      "target-triplet": "x86_64-any-linux", 
      "version": "0.9.0"
    }, 
    "zipline-0.9.0-np19py34_0.tar.bz2": {
      "arch": "x86_64", 
      "binstar": {
        "channel": "main", 
        "owner_id": "52fa7ff95e76835e23a64c25", 
        "package_id": "53051f135e76835e253b1310"
      }, 
      "build": "np19py34_0", 
      "build_number": 0, 
      "depends": [
        "bcolz >=0.12.1", 
        "bottleneck >=1.0.0", 
        "click >=4.0.0", 
        "contextlib2 >=0.4.0", 
        "cyordereddict >=0.2.2", 
        "cython >=0.22.1", 
        "decorator >=4.0.0", 
        "logbook >=0.12.5", 
        "networkx >=1.9.1", 
        "numexpr >=2.4.6", 
        "numpy 1.9*", 
        "pandas >=0.16.1", 
        "patsy >=0.4.0", 
        "pip >=7.1.0", 
        "python 3.4*", 
        "python-dateutil >=2.4.2", 
        "pytz >=2015.4", 
        "requests >=2.9.1", 
        "scipy >=0.15.1", 
        "setuptools >18.0", 
        "six >=1.10.0", 
        "sqlalchemy >=1.0.8", 
        "statsmodels >=0.6.1", 
        "toolz >=0.7.4"
      ], 
      "license": "Apache Software License", 
      "machine": "x86_64", 
      "md5": "f808c2b40adb79aef6ca26dbad15c481", 
      "name": "zipline", 
      "operatingsystem": "linux", 
      "platform": "linux", 
      "requires": [], 
      "size": 2029355, 
      "subdir": "linux-64", 
      "target-triplet": "x86_64-any-linux", 
      "version": "0.9.0"
    }, 
    "zipline-1.0.0-np110py27_0.tar.bz2": {
      "arch": "x86_64", 
      "binstar": {
        "channel": "main", 
        "owner_id": "52fa7ff95e76835e23a64c25", 
        "package_id": "53051f135e76835e253b1310"
      }, 
      "build": "np110py27_0", 
      "build_number": 0, 
      "depends": [
        "bcolz >=0.12.1,<1", 
        "bottleneck >=1.0.0", 
        "cachetools >=1.1.5", 
        "click >=4.0.0", 
        "contextlib2 >=0.4.0", 
        "cyordereddict >=0.2.2", 
        "cython >=0.22.1", 
        "decorator >=4.0.0", 
        "intervaltree >=2.1.0", 
        "logbook >=0.12.5", 
        "multipledispatch >=0.4.8", 
        "networkx >=1.9.1", 
        "numexpr >=2.4.6", 
        "numpy 1.10*", 
        "pandas >=0.17.1,<0.18", 
        "pandas-datareader >=0.2.1", 
        "patsy >=0.4.0", 
        "pip >=7.1.0", 
        "python 2.7*", 
        "python-dateutil >=2.4.2", 
        "pytz >=2015.4", 
        "requests >=2.9.1", 
        "scipy >=0.16.1", 
        "setuptools >18.0", 
        "six >=1.10.0", 
        "sortedcontainers >=1.4.4", 
        "sqlalchemy >=1.0.8", 
        "statsmodels >=0.6.1", 
        "toolz >=0.7.4"
      ], 
      "license": "Apache Software License", 
      "machine": "x86_64", 
      "md5": "3d5957390f7d406ffd554bf6b014d2cf", 
      "name": "zipline", 
      "operatingsystem": "linux", 
      "platform": "linux", 
      "requires": [], 
      "size": 2876036, 
      "subdir": "linux-64", 
      "target-triplet": "x86_64-any-linux", 
      "version": "1.0.0"
    }, 
    "zipline-1.0.0-np110py34_0.tar.bz2": {
      "arch": "x86_64", 
      "binstar": {
        "channel": "main", 
        "owner_id": "52fa7ff95e76835e23a64c25", 
        "package_id": "53051f135e76835e253b1310"
      }, 
      "build": "np110py34_0", 
      "build_number": 0, 
      "depends": [
        "bcolz >=0.12.1,<1", 
        "bottleneck >=1.0.0", 
        "cachetools >=1.1.5", 
        "click >=4.0.0", 
        "contextlib2 >=0.4.0", 
        "cyordereddict >=0.2.2", 
        "cython >=0.22.1", 
        "decorator >=4.0.0", 
        "intervaltree >=2.1.0", 
        "logbook >=0.12.5", 
        "multipledispatch >=0.4.8", 
        "networkx >=1.9.1", 
        "numexpr >=2.4.6", 
        "numpy 1.10*", 
        "pandas >=0.17.1,<0.18", 
        "pandas-datareader >=0.2.1", 
        "patsy >=0.4.0", 
        "pip >=7.1.0", 
        "python 3.4*", 
        "python-dateutil >=2.4.2", 
        "pytz >=2015.4", 
        "requests >=2.9.1", 
        "scipy >=0.16.1", 
        "setuptools >18.0", 
        "six >=1.10.0", 
        "sortedcontainers >=1.4.4", 
        "sqlalchemy >=1.0.8", 
        "statsmodels >=0.6.1", 
        "toolz >=0.7.4"
      ], 
      "license": "Apache Software License", 
      "machine": "x86_64", 
      "md5": "2b11058d8edd1d08e5e2b2951c2b7398", 
      "name": "zipline", 
      "operatingsystem": "linux", 
      "platform": "linux", 
      "requires": [], 
      "size": 3057184, 
      "subdir": "linux-64", 
      "target-triplet": "x86_64-any-linux", 
      "version": "1.0.0"
    }, 
    "zipline-1.0.0-np19py27_0.tar.bz2": {
      "arch": "x86_64", 
      "binstar": {
        "channel": "main", 
        "owner_id": "52fa7ff95e76835e23a64c25", 
        "package_id": "53051f135e76835e253b1310"
      }, 
      "build": "np19py27_0", 
      "build_number": 0, 
      "depends": [
        "bcolz >=0.12.1,<1", 
        "bottleneck >=1.0.0", 
        "cachetools >=1.1.5", 
        "click >=4.0.0", 
        "contextlib2 >=0.4.0", 
        "cyordereddict >=0.2.2", 
        "cython >=0.22.1", 
        "decorator >=4.0.0", 
        "intervaltree >=2.1.0", 
        "logbook >=0.12.5", 
        "multipledispatch >=0.4.8", 
        "networkx >=1.9.1", 
        "numexpr >=2.4.6", 
        "numpy 1.9*", 
        "pandas >=0.16.1,<0.18", 
        "pandas-datareader >=0.2.1", 
        "patsy >=0.4.0", 
        "pip >=7.1.0", 
        "python 2.7*", 
        "python-dateutil >=2.4.2", 
        "pytz >=2015.4", 
        "requests >=2.9.1", 
        "scipy >=0.15.1", 
        "setuptools >18.0", 
        "six >=1.10.0", 
        "sortedcontainers >=1.4.4", 
        "sqlalchemy >=1.0.8", 
        "statsmodels >=0.6.1", 
        "toolz >=0.7.4"
      ], 
      "license": "Apache Software License", 
      "machine": "x86_64", 
      "md5": "7643b261a4e4c193dfd6e40ac91a6631", 
      "name": "zipline", 
      "operatingsystem": "linux", 
      "platform": "linux", 
      "requires": [], 
      "size": 2874963, 
      "subdir": "linux-64", 
      "target-triplet": "x86_64-any-linux", 
      "version": "1.0.0"
    }, 
    "zipline-1.0.0-np19py34_0.tar.bz2": {
      "arch": "x86_64", 
      "binstar": {
        "channel": "main", 
        "owner_id": "52fa7ff95e76835e23a64c25", 
        "package_id": "53051f135e76835e253b1310"
      }, 
      "build": "np19py34_0", 
      "build_number": 0, 
      "depends": [
        "bcolz >=0.12.1,<1", 
        "bottleneck >=1.0.0", 
        "cachetools >=1.1.5", 
        "click >=4.0.0", 
        "contextlib2 >=0.4.0", 
        "cyordereddict >=0.2.2", 
        "cython >=0.22.1", 
        "decorator >=4.0.0", 
        "intervaltree >=2.1.0", 
        "logbook >=0.12.5", 
        "multipledispatch >=0.4.8", 
        "networkx >=1.9.1", 
        "numexpr >=2.4.6", 
        "numpy 1.9*", 
        "pandas >=0.16.1,<0.18", 
        "pandas-datareader >=0.2.1", 
        "patsy >=0.4.0", 
        "pip >=7.1.0", 
        "python 3.4*", 
        "python-dateutil >=2.4.2", 
        "pytz >=2015.4", 
        "requests >=2.9.1", 
        "scipy >=0.15.1", 
        "setuptools >18.0", 
        "six >=1.10.0", 
        "sortedcontainers >=1.4.4", 
        "sqlalchemy >=1.0.8", 
        "statsmodels >=0.6.1", 
        "toolz >=0.7.4"
      ], 
      "license": "Apache Software License", 
      "machine": "x86_64", 
      "md5": "a7e994d7b54269540210c22177e02a84", 
      "name": "zipline", 
      "operatingsystem": "linux", 
      "platform": "linux", 
      "requires": [], 
      "size": 3056735, 
      "subdir": "linux-64", 
      "target-triplet": "x86_64-any-linux", 
      "version": "1.0.0"
    }, 
    "zipline-1.0.1-np110py27_2_g85327d8.tar.bz2": {
      "arch": "x86_64", 
      "binstar": {
        "channel": "main", 
        "owner_id": "52fa7ff95e76835e23a64c25", 
        "package_id": "53051f135e76835e253b1310"
      }, 
      "build": "np110py27_2_g85327d8", 
      "build_number": 2, 
      "depends": [
        "bcolz >=0.12.1,<1", 
        "bottleneck >=1.0.0", 
        "cachetools >=1.1.5", 
        "click >=4.0.0", 
        "contextlib2 >=0.4.0", 
        "cyordereddict >=0.2.2", 
        "cython >=0.22.1", 
        "decorator >=4.0.0", 
        "intervaltree >=2.1.0", 
        "logbook >=0.12.5", 
        "multipledispatch >=0.4.8", 
        "networkx >=1.9.1", 
        "numexpr >=2.4.6", 
        "numpy 1.10*", 
        "pandas >=0.17.1,<0.18", 
        "pandas-datareader >=0.2.1", 
        "patsy >=0.4.0", 
        "pip >=7.1.0", 
        "python 2.7*", 
        "python-dateutil >=2.4.2", 
        "pytz >=2015.4", 
        "requests >=2.9.1", 
        "scipy >=0.16.1", 
        "setuptools >18.0", 
        "six >=1.10.0", 
        "sortedcontainers >=1.4.4", 
        "sqlalchemy >=1.0.8", 
        "statsmodels >=0.6.1", 
        "toolz >=0.7.4"
      ], 
      "license": "Apache Software License", 
      "machine": "x86_64", 
      "md5": "a2d4d77d6068e100b3451b9e623af42e", 
      "name": "zipline", 
      "operatingsystem": "linux", 
      "platform": "linux", 
      "requires": [], 
      "size": 2880332, 
      "subdir": "linux-64", 
      "target-triplet": "x86_64-any-linux", 
      "version": "1.0.1"
    }, 
    "zipline-1.0.1-np110py34_2_g85327d8.tar.bz2": {
      "arch": "x86_64", 
      "binstar": {
        "channel": "main", 
        "owner_id": "52fa7ff95e76835e23a64c25", 
        "package_id": "53051f135e76835e253b1310"
      }, 
      "build": "np110py34_2_g85327d8", 
      "build_number": 2, 
      "depends": [
        "bcolz >=0.12.1,<1", 
        "bottleneck >=1.0.0", 
        "cachetools >=1.1.5", 
        "click >=4.0.0", 
        "contextlib2 >=0.4.0", 
        "cyordereddict >=0.2.2", 
        "cython >=0.22.1", 
        "decorator >=4.0.0", 
        "intervaltree >=2.1.0", 
        "logbook >=0.12.5", 
        "multipledispatch >=0.4.8", 
        "networkx >=1.9.1", 
        "numexpr >=2.4.6", 
        "numpy 1.10*", 
        "pandas >=0.17.1,<0.18", 
        "pandas-datareader >=0.2.1", 
        "patsy >=0.4.0", 
        "pip >=7.1.0", 
        "python 3.4*", 
        "python-dateutil >=2.4.2", 
        "pytz >=2015.4", 
        "requests >=2.9.1", 
        "scipy >=0.16.1", 
        "setuptools >18.0", 
        "six >=1.10.0", 
        "sortedcontainers >=1.4.4", 
        "sqlalchemy >=1.0.8", 
        "statsmodels >=0.6.1", 
        "toolz >=0.7.4"
      ], 
      "license": "Apache Software License", 
      "machine": "x86_64", 
      "md5": "2b90af24352db8e071a7bd8c644ee9d8", 
      "name": "zipline", 
      "operatingsystem": "linux", 
      "platform": "linux", 
      "requires": [], 
      "size": 3064910, 
      "subdir": "linux-64", 
      "target-triplet": "x86_64-any-linux", 
      "version": "1.0.1"
    }, 
    "zipline-1.0.1-np19py27_2_g85327d8.tar.bz2": {
      "arch": "x86_64", 
      "binstar": {
        "channel": "main", 
        "owner_id": "52fa7ff95e76835e23a64c25", 
        "package_id": "53051f135e76835e253b1310"
      }, 
      "build": "np19py27_2_g85327d8", 
      "build_number": 2, 
      "depends": [
        "bcolz >=0.12.1,<1", 
        "bottleneck >=1.0.0", 
        "cachetools >=1.1.5", 
        "click >=4.0.0", 
        "contextlib2 >=0.4.0", 
        "cyordereddict >=0.2.2", 
        "cython >=0.22.1", 
        "decorator >=4.0.0", 
        "intervaltree >=2.1.0", 
        "libgfortran ==1", 
        "logbook >=0.12.5", 
        "multipledispatch >=0.4.8", 
        "networkx >=1.9.1", 
        "numexpr >=2.4.6", 
        "numpy 1.9*", 
        "pandas >=0.16.1,<0.18", 
        "pandas-datareader >=0.2.1", 
        "patsy >=0.4.0", 
        "pip >=7.1.0", 
        "python 2.7*", 
        "python-dateutil >=2.4.2", 
        "pytz >=2015.4", 
        "requests >=2.9.1", 
        "scipy >=0.15.1", 
        "setuptools >18.0", 
        "six >=1.10.0", 
        "sortedcontainers >=1.4.4", 
        "sqlalchemy >=1.0.8", 
        "statsmodels >=0.6.1", 
        "toolz >=0.7.4"
      ], 
      "license": "Apache Software License", 
      "machine": "x86_64", 
      "md5": "0cc4ef9a059383e27b78749d00be8d82", 
      "name": "zipline", 
      "operatingsystem": "linux", 
      "platform": "linux", 
      "requires": [], 
      "size": 2880131, 
      "subdir": "linux-64", 
      "target-triplet": "x86_64-any-linux", 
      "version": "1.0.1"
    }, 
    "zipline-1.0.1-np19py34_2_g85327d8.tar.bz2": {
      "arch": "x86_64", 
      "binstar": {
        "channel": "main", 
        "owner_id": "52fa7ff95e76835e23a64c25", 
        "package_id": "53051f135e76835e253b1310"
      }, 
      "build": "np19py34_2_g85327d8", 
      "build_number": 2, 
      "depends": [
        "bcolz >=0.12.1,<1", 
        "bottleneck >=1.0.0", 
        "cachetools >=1.1.5", 
        "click >=4.0.0", 
        "contextlib2 >=0.4.0", 
        "cyordereddict >=0.2.2", 
        "cython >=0.22.1", 
        "decorator >=4.0.0", 
        "intervaltree >=2.1.0", 
        "libgfortran ==1", 
        "logbook >=0.12.5", 
        "multipledispatch >=0.4.8", 
        "networkx >=1.9.1", 
        "numexpr >=2.4.6", 
        "numpy 1.9*", 
        "pandas >=0.16.1,<0.18", 
        "pandas-datareader >=0.2.1", 
        "patsy >=0.4.0", 
        "pip >=7.1.0", 
        "python 3.4*", 
        "python-dateutil >=2.4.2", 
        "pytz >=2015.4", 
        "requests >=2.9.1", 
        "scipy >=0.15.1", 
        "setuptools >18.0", 
        "six >=1.10.0", 
        "sortedcontainers >=1.4.4", 
        "sqlalchemy >=1.0.8", 
        "statsmodels >=0.6.1", 
        "toolz >=0.7.4"
      ], 
      "license": "Apache Software License", 
      "machine": "x86_64", 
      "md5": "39bb1f7ac1052b551137c48913cfd1ca", 
      "name": "zipline", 
      "operatingsystem": "linux", 
      "platform": "linux", 
      "requires": [], 
      "size": 3062522, 
      "subdir": "linux-64", 
      "target-triplet": "x86_64-any-linux", 
      "version": "1.0.1"
    }, 
    "zipline-1.0.2-np110py27_0.tar.bz2": {
      "arch": "x86_64", 
      "binstar": {
        "channel": "main", 
        "owner_id": "52fa7ff95e76835e23a64c25", 
        "package_id": "53051f135e76835e253b1310"
      }, 
      "build": "np110py27_0", 
      "build_number": 0, 
      "depends": [
        "alembic >=0.7.7", 
        "bcolz >=0.12.1,<1", 
        "bottleneck >=1.0.0", 
        "cachetools >=1.1.5", 
        "click >=4.0.0", 
        "contextlib2 >=0.4.0", 
        "cyordereddict >=0.2.2", 
        "cython >=0.22.1", 
        "decorator >=4.0.0", 
        "empyrical >=0.1.11", 
        "intervaltree >=2.1.0", 
        "logbook >=0.12.5", 
        "multipledispatch >=0.4.8", 
        "networkx >=1.9.1", 
        "numexpr >=2.4.6", 
        "numpy 1.10*", 
        "pandas >=0.16.1,<0.18", 
        "pandas-datareader >=0.2.1", 
        "patsy >=0.4.0", 
        "pip >=7.1.0", 
        "python 2.7*", 
        "python-dateutil >=2.4.2", 
        "pytz >=2015.4", 
        "requests >=2.9.1", 
        "scipy >=0.15.1", 
        "setuptools >18.0", 
        "six >=1.10.0", 
        "sortedcontainers >=1.4.4", 
        "sqlalchemy >=1.0.8", 
        "statsmodels >=0.6.1", 
        "toolz >=0.7.4"
      ], 
      "has_prefix": true, 
      "license": "Apache Software License", 
      "machine": "x86_64", 
      "md5": "02f272d2e0986c2e0319ff61b85ebeb4", 
      "name": "zipline", 
      "operatingsystem": "linux", 
      "platform": "linux", 
      "requires": [], 
      "size": 2989097, 
      "subdir": "linux-64", 
      "target-triplet": "x86_64-any-linux", 
      "version": "1.0.2"
    }, 
    "zipline-1.0.2-np110py34_0.tar.bz2": {
      "arch": "x86_64", 
      "binstar": {
        "channel": "main", 
        "owner_id": "52fa7ff95e76835e23a64c25", 
        "package_id": "53051f135e76835e253b1310"
      }, 
      "build": "np110py34_0", 
      "build_number": 0, 
      "depends": [
        "alembic >=0.7.7", 
        "bcolz >=0.12.1,<1", 
        "bottleneck >=1.0.0", 
        "cachetools >=1.1.5", 
        "click >=4.0.0", 
        "contextlib2 >=0.4.0", 
        "cyordereddict >=0.2.2", 
        "cython >=0.22.1", 
        "decorator >=4.0.0", 
        "empyrical >=0.1.11", 
        "intervaltree >=2.1.0", 
        "logbook >=0.12.5", 
        "multipledispatch >=0.4.8", 
        "networkx >=1.9.1", 
        "numexpr >=2.4.6", 
        "numpy 1.10*", 
        "pandas >=0.16.1,<0.18", 
        "pandas-datareader >=0.2.1", 
        "patsy >=0.4.0", 
        "pip >=7.1.0", 
        "python 3.4*", 
        "python-dateutil >=2.4.2", 
        "pytz >=2015.4", 
        "requests >=2.9.1", 
        "scipy >=0.15.1", 
        "setuptools >18.0", 
        "six >=1.10.0", 
        "sortedcontainers >=1.4.4", 
        "sqlalchemy >=1.0.8", 
        "statsmodels >=0.6.1", 
        "toolz >=0.7.4"
      ], 
      "has_prefix": true, 
      "license": "Apache Software License", 
      "machine": "x86_64", 
      "md5": "94f486c43dc85241d7e4a5adcdcd6cc9", 
      "name": "zipline", 
      "operatingsystem": "linux", 
      "platform": "linux", 
      "requires": [], 
      "size": 3101676, 
      "subdir": "linux-64", 
      "target-triplet": "x86_64-any-linux", 
      "version": "1.0.2"
    }, 
    "zipline-1.0.2-np19py27_0.tar.bz2": {
      "arch": "x86_64", 
      "binstar": {
        "channel": "main", 
        "owner_id": "52fa7ff95e76835e23a64c25", 
        "package_id": "53051f135e76835e253b1310"
      }, 
      "build": "np19py27_0", 
      "build_number": 0, 
      "depends": [
        "alembic >=0.7.7", 
        "bcolz >=0.12.1,<1", 
        "bottleneck >=1.0.0", 
        "cachetools >=1.1.5", 
        "click >=4.0.0", 
        "contextlib2 >=0.4.0", 
        "cyordereddict >=0.2.2", 
        "cython >=0.22.1", 
        "decorator >=4.0.0", 
        "empyrical >=0.1.11", 
        "intervaltree >=2.1.0", 
        "libgfortran ==1", 
        "logbook >=0.12.5", 
        "multipledispatch >=0.4.8", 
        "networkx >=1.9.1", 
        "numexpr >=2.4.6", 
        "numpy 1.9*", 
        "pandas >=0.16.1,<0.18", 
        "pandas-datareader >=0.2.1", 
        "patsy >=0.4.0", 
        "pip >=7.1.0", 
        "python 2.7*", 
        "python-dateutil >=2.4.2", 
        "pytz >=2015.4", 
        "requests >=2.9.1", 
        "scipy >=0.15.1", 
        "setuptools >18.0", 
        "six >=1.10.0", 
        "sortedcontainers >=1.4.4", 
        "sqlalchemy >=1.0.8", 
        "statsmodels >=0.6.1", 
        "toolz >=0.7.4"
      ], 
      "has_prefix": true, 
      "license": "Apache Software License", 
      "machine": "x86_64", 
      "md5": "592bcf3a908b3f2aa7463ffc37283c73", 
      "name": "zipline", 
      "operatingsystem": "linux", 
      "platform": "linux", 
      "requires": [], 
      "size": 2988972, 
      "subdir": "linux-64", 
      "target-triplet": "x86_64-any-linux", 
      "version": "1.0.2"
    }, 
    "zipline-1.0.2-np19py34_0.tar.bz2": {
      "arch": "x86_64", 
      "binstar": {
        "channel": "main", 
        "owner_id": "52fa7ff95e76835e23a64c25", 
        "package_id": "53051f135e76835e253b1310"
      }, 
      "build": "np19py34_0", 
      "build_number": 0, 
      "depends": [
        "alembic >=0.7.7", 
        "bcolz >=0.12.1,<1", 
        "bottleneck >=1.0.0", 
        "cachetools >=1.1.5", 
        "click >=4.0.0", 
        "contextlib2 >=0.4.0", 
        "cyordereddict >=0.2.2", 
        "cython >=0.22.1", 
        "decorator >=4.0.0", 
        "empyrical >=0.1.11", 
        "intervaltree >=2.1.0", 
        "libgfortran ==1", 
        "logbook >=0.12.5", 
        "multipledispatch >=0.4.8", 
        "networkx >=1.9.1", 
        "numexpr >=2.4.6", 
        "numpy 1.9*", 
        "pandas >=0.16.1,<0.18", 
        "pandas-datareader >=0.2.1", 
        "patsy >=0.4.0", 
        "pip >=7.1.0", 
        "python 3.4*", 
        "python-dateutil >=2.4.2", 
        "pytz >=2015.4", 
        "requests >=2.9.1", 
        "scipy >=0.15.1", 
        "setuptools >18.0", 
        "six >=1.10.0", 
        "sortedcontainers >=1.4.4", 
        "sqlalchemy >=1.0.8", 
        "statsmodels >=0.6.1", 
        "toolz >=0.7.4"
      ], 
      "has_prefix": true, 
      "license": "Apache Software License", 
      "machine": "x86_64", 
      "md5": "e84c112ba87829ae80ec051b541c6fbb", 
      "name": "zipline", 
      "operatingsystem": "linux", 
      "platform": "linux", 
      "requires": [], 
      "size": 3100977, 
      "subdir": "linux-64", 
      "target-triplet": "x86_64-any-linux", 
      "version": "1.0.2"
    }, 
    "zipline-1.1.0-np111py27_0.tar.bz2": {
      "arch": "x86_64", 
      "binstar": {
        "channel": "main", 
        "owner_id": "52fa7ff95e76835e23a64c25", 
        "package_id": "53051f135e76835e253b1310"
      }, 
      "build": "np111py27_0", 
      "build_number": 0, 
      "depends": [
        "alembic >=0.7.7", 
        "bcolz >=0.12.1,<1", 
        "bottleneck >=1.0.0", 
        "click >=4.0.0", 
        "contextlib2 >=0.4.0", 
        "cyordereddict >=0.2.2", 
        "cython >=0.22.1", 
        "decorator >=4.0.0", 
        "empyrical >=0.2.2", 
        "intervaltree >=2.1.0", 
        "logbook >=0.12.5", 
        "lru-dict >=1.1.4", 
        "mako >=1.0.1", 
        "markupsafe >=0.23", 
        "multipledispatch >=0.4.8", 
        "networkx >=1.9.1", 
        "numexpr >=2.6.1", 
        "numpy 1.11*", 
        "pandas >=0.18.1,<0.19", 
        "pandas-datareader >=0.2.1", 
        "patsy >=0.4.0", 
        "pip >=7.1.0", 
        "pytables >=3.3.0", 
        "python 2.7*", 
        "python-dateutil >=2.4.2", 
        "pytz >=2016.4", 
        "requests >=2.9.1", 
        "requests-file >=1.4.1", 
        "scipy >=0.17.1", 
        "setuptools >18.0", 
        "six >=1.10.0", 
        "sortedcontainers >=1.4.4", 
        "sqlalchemy >=1.0.8", 
        "statsmodels >=0.6.1", 
        "toolz >=0.8.2"
      ], 
      "has_prefix": true, 
      "license": "Apache Software License", 
      "machine": "x86_64", 
      "md5": "79fac4fcb308ff608e1798d4d104fc8d", 
      "name": "zipline", 
      "operatingsystem": "linux", 
      "platform": "linux", 
      "requires": [], 
      "size": 3755712, 
      "subdir": "linux-64", 
      "target-triplet": "x86_64-any-linux", 
      "version": "1.1.0"
    }, 
    "zipline-1.1.0-np111py34_0.tar.bz2": {
      "arch": "x86_64", 
      "binstar": {
        "channel": "main", 
        "owner_id": "52fa7ff95e76835e23a64c25", 
        "package_id": "53051f135e76835e253b1310"
      }, 
      "build": "np111py34_0", 
      "build_number": 0, 
      "depends": [
        "alembic >=0.7.7", 
        "bcolz >=0.12.1,<1", 
        "bottleneck >=1.0.0", 
        "click >=4.0.0", 
        "contextlib2 >=0.4.0", 
        "cyordereddict >=0.2.2", 
        "cython >=0.22.1", 
        "decorator >=4.0.0", 
        "empyrical >=0.2.2", 
        "intervaltree >=2.1.0", 
        "logbook >=0.12.5", 
        "lru-dict >=1.1.4", 
        "mako >=1.0.1", 
        "markupsafe >=0.23", 
        "multipledispatch >=0.4.8", 
        "networkx >=1.9.1", 
        "numexpr >=2.6.1", 
        "numpy 1.11*", 
        "pandas >=0.18.1,<0.19", 
        "pandas-datareader >=0.2.1", 
        "patsy >=0.4.0", 
        "pip >=7.1.0", 
        "pytables >=3.3.0", 
        "python 3.4*", 
        "python-dateutil >=2.4.2", 
        "pytz >=2016.4", 
        "requests >=2.9.1", 
        "requests-file >=1.4.1", 
        "scipy >=0.17.1", 
        "setuptools >18.0", 
        "six >=1.10.0", 
        "sortedcontainers >=1.4.4", 
        "sqlalchemy >=1.0.8", 
        "statsmodels >=0.6.1", 
        "toolz >=0.8.2"
      ], 
      "has_prefix": true, 
      "license": "Apache Software License", 
      "machine": "x86_64", 
      "md5": "9221a37c01cc0655122bd0415c3157a6", 
      "name": "zipline", 
      "operatingsystem": "linux", 
      "platform": "linux", 
      "requires": [], 
      "size": 3950842, 
      "subdir": "linux-64", 
      "target-triplet": "x86_64-any-linux", 
      "version": "1.1.0"
    }, 
    "zipline-1.1.1-np111py27_0.tar.bz2": {
      "arch": "x86_64", 
      "binstar": {
        "channel": "main", 
        "owner_id": "52fa7ff95e76835e23a64c25", 
        "package_id": "53051f135e76835e253b1310"
      }, 
      "build": "np111py27_0", 
      "build_number": 0, 
      "depends": [
        "alembic >=0.7.7", 
        "bcolz >=0.12.1,<1", 
        "bottleneck >=1.0.0", 
        "click >=4.0.0", 
        "contextlib2 >=0.4.0", 
        "cyordereddict >=0.2.2", 
        "cython >=0.25.2", 
        "decorator >=4.0.0", 
        "empyrical >=0.2.2", 
        "intervaltree >=2.1.0", 
        "logbook >=0.12.5", 
        "lru-dict >=1.1.4", 
        "mako >=1.0.1", 
        "markupsafe >=0.23", 
        "multipledispatch >=0.4.8", 
        "networkx >=1.9.1", 
        "numexpr >=2.6.1", 
        "numpy 1.11*", 
        "pandas >=0.18.1,<0.19", 
        "pandas-datareader >=0.2.1", 
        "patsy >=0.4.0", 
        "pip >=7.1.0", 
        "pytables >=3.3.0", 
        "python 2.7*", 
        "python-dateutil >=2.4.2", 
        "pytz >=2016.4", 
        "requests >=2.9.1", 
        "requests-file >=1.4.1", 
        "scipy >=0.17.1", 
        "setuptools >18.0", 
        "six >=1.10.0", 
        "sortedcontainers >=1.4.4", 
        "sqlalchemy >=1.0.8", 
        "statsmodels >=0.6.1", 
        "toolz >=0.8.2"
      ], 
      "has_prefix": true, 
      "license": "Apache Software License", 
      "machine": "x86_64", 
      "md5": "abfa6de71b1b5301b47a9092aea2aa66", 
      "name": "zipline", 
      "operatingsystem": "linux", 
      "platform": "linux", 
      "requires": [], 
      "size": 4017394, 
      "subdir": "linux-64", 
      "target-triplet": "x86_64-any-linux", 
      "version": "1.1.1"
    }, 
    "zipline-1.1.1-np111py34_0.tar.bz2": {
      "arch": "x86_64", 
      "binstar": {
        "channel": "main", 
        "owner_id": "52fa7ff95e76835e23a64c25", 
        "package_id": "53051f135e76835e253b1310"
      }, 
      "build": "np111py34_0", 
      "build_number": 0, 
      "depends": [
        "alembic >=0.7.7", 
        "bcolz >=0.12.1,<1", 
        "bottleneck >=1.0.0", 
        "click >=4.0.0", 
        "contextlib2 >=0.4.0", 
        "cyordereddict >=0.2.2", 
        "cython >=0.25.2", 
        "decorator >=4.0.0", 
        "empyrical >=0.2.2", 
        "intervaltree >=2.1.0", 
        "logbook >=0.12.5", 
        "lru-dict >=1.1.4", 
        "mako >=1.0.1", 
        "markupsafe >=0.23", 
        "multipledispatch >=0.4.8", 
        "networkx >=1.9.1", 
        "numexpr >=2.6.1", 
        "numpy 1.11*", 
        "pandas >=0.18.1,<0.19", 
        "pandas-datareader >=0.2.1", 
        "patsy >=0.4.0", 
        "pip >=7.1.0", 
        "pytables >=3.3.0", 
        "python 3.4*", 
        "python-dateutil >=2.4.2", 
        "pytz >=2016.4", 
        "requests >=2.9.1", 
        "requests-file >=1.4.1", 
        "scipy >=0.17.1", 
        "setuptools >18.0", 
        "six >=1.10.0", 
        "sortedcontainers >=1.4.4", 
        "sqlalchemy >=1.0.8", 
        "statsmodels >=0.6.1", 
        "toolz >=0.8.2"
      ], 
      "has_prefix": true, 
      "license": "Apache Software License", 
      "machine": "x86_64", 
      "md5": "19fbd67afb272661d06713fd695663e6", 
      "name": "zipline", 
      "operatingsystem": "linux", 
      "platform": "linux", 
      "requires": [], 
      "size": 4316596, 
      "subdir": "linux-64", 
      "target-triplet": "x86_64-any-linux", 
      "version": "1.1.1"
    }, 
    "zipline-1.1.1-np111py35_0.tar.bz2": {
      "arch": "x86_64", 
      "binstar": {
        "channel": "main", 
        "owner_id": "52fa7ff95e76835e23a64c25", 
        "package_id": "53051f135e76835e253b1310"
      }, 
      "build": "np111py35_0", 
      "build_number": 0, 
      "depends": [
        "alembic >=0.7.7", 
        "bcolz >=0.12.1,<1", 
        "bottleneck >=1.0.0", 
        "click >=4.0.0", 
        "contextlib2 >=0.4.0", 
        "cyordereddict >=0.2.2", 
        "cython >=0.25.2", 
        "decorator >=4.0.0", 
        "empyrical >=0.2.2", 
        "intervaltree >=2.1.0", 
        "logbook >=0.12.5", 
        "lru-dict >=1.1.4", 
        "mako >=1.0.1", 
        "markupsafe >=0.23", 
        "multipledispatch >=0.4.8", 
        "networkx >=1.9.1", 
        "numexpr >=2.6.1", 
        "numpy 1.11*", 
        "pandas >=0.18.1,<0.19", 
        "pandas-datareader >=0.2.1", 
        "patsy >=0.4.0", 
        "pip >=7.1.0", 
        "pytables >=3.3.0", 
        "python 3.5*", 
        "python-dateutil >=2.4.2", 
        "pytz >=2016.4", 
        "requests >=2.9.1", 
        "requests-file >=1.4.1", 
        "scipy >=0.17.1", 
        "setuptools >18.0", 
        "six >=1.10.0", 
        "sortedcontainers >=1.4.4", 
        "sqlalchemy >=1.0.8", 
        "statsmodels >=0.6.1", 
        "toolz >=0.8.2"
      ], 
      "has_prefix": true, 
      "license": "Apache Software License", 
      "machine": "x86_64", 
      "md5": "45a228230c009c8cb7669b2f6f6a2bb4", 
      "name": "zipline", 
      "operatingsystem": "linux", 
      "platform": "linux", 
      "requires": [], 
      "size": 4205055, 
      "subdir": "linux-64", 
      "target-triplet": "x86_64-any-linux", 
      "version": "1.1.1"
    }
  }
}